Workbook

Sheet Executive Summary
B2: Indian Patent Portfolio — Client & Due Date Analysis
B3: Snapshot report generated from filing / RQ (Request for Examination) data. RQ deadline figures recalculate live against today's date.
B5: Total Cases | D5: Unique Clients | F5: Pending RQ (Active) | H5: Overdue RQ
B6: =COUNTA(Data!B2:B6232) -> 6052 | D6: =COUNTA('Client Summary'!A2:A607) -> 606 | F6: =SUM('Client Summary'!J2:J607) -> 1227 | H6: =SUM('Client Summary'!K2:K607) -> 788
B10: RQ Urgency (Active Cases) | E10: Top 10 Clients — Overdue + Due-Soon RQ Filings
B11: Urgency | C11: Count | E11: Client Name | F11: Overdue | G11: Due >=90d | H11: Next RQ Due
B12: OVERDUE | C12: =SUMPRODUCT(('Pending RQ Deadlines'!$J$2:$J$1271="OVERDUE")*('Pending RQ Deadlines'!$K$2:$K$1271="Yes")) -> 747 | E12: =IF(LARGE('Client Summary'!$N$2:$N$607,1)<=0,"",INDEX('Client Summary'!$A$2:$A$607,MATCH(LARGE('Client Summary'!$N$2:$N$607,1),'Client Summary'!$N$2:$N$607,0))) -> ZUMUTOR BIOLOGICS, INC. | F12: =IF(LARGE('Client Summary'!$N$2:$N$607,1)<=0,"",INDEX('Client Summary'!$K$2:$K$607,MATCH(LARGE('Client Summary'!$N$2:$N$607,1),'Client Summary'!$N$2:$N$607,0))) -> 1 | G12: =IF(LARGE('Client Summary'!$N$2:$N$607,1)<=0,"",INDEX('Client Summary'!$L$2:$L$607,MATCH(LARGE('Client Summary'!$N$2:$N$607,1),'Client Summary'!$N$2:$N$607,0))) -> 1 | H12: =IF(LARGE('Client Summary'!$N$2:$N$607,1)<=0,"",INDEX('Client Summary'!$M$2:$M$607,MATCH(LARGE('Client Summary'!$N$2:$N$607,1),'Client Summary'!$N$2:$N$607,0)))
B13: DUE <=30 DAYS | C13: =SUMPRODUCT(('Pending RQ Deadlines'!$J$2:$J$1271="DUE <=30 DAYS")*('Pending RQ Deadlines'!$K$2:$K$1271="Yes")) -> 3 | E13: =IF(LARGE('Client Summary'!$N$2:$N$607,2)<=0,"",INDEX('Client Summary'!$A$2:$A$607,MATCH(LARGE('Client Summary'!$N$2:$N$607,2),'Client Summary'!$N$2:$N$607,0))) -> 3B PHARMACEUTICALS GMBH | F13: =IF(LARGE('Client Summary'!$N$2:$N$607,2)<=0,"",INDEX('Client Summary'!$K$2:$K$607,MATCH(LARGE('Client Summary'!$N$2:$N$607,2),'Client Summary'!$N$2:$N$607,0))) -> 0 | G13: =IF(LARGE('Client Summary'!$N$2:$N$607,2)<=0,"",INDEX('Client Summary'!$L$2:$L$607,MATCH(LARGE('Client Summary'!$N$2:$N$607,2),'Client Summary'!$N$2:$N$607,0))) -> 0 | H13: =IF(LARGE('Client Summary'!$N$2:$N$607,2)<=0,"",INDEX('Client Summary'!$M$2:$M$607,MATCH(LARGE('Client Summary'!$N$2:$N$607,2),'Client Summary'!$N$2:$N$607,0)))
B14: DUE <=90 DAYS | C14: =SUMPRODUCT(('Pending RQ Deadlines'!$J$2:$J$1271="DUE <=90 DAYS")*('Pending RQ Deadlines'!$K$2:$K$1271="Yes")) -> 1 | E14: =IF(LARGE('Client Summary'!$N$2:$N$607,3)<=0,"",INDEX('Client Summary'!$A$2:$A$607,MATCH(LARGE('Client Summary'!$N$2:$N$607,3),'Client Summary'!$N$2:$N$607,0))) -> ACTEGA GmbH | F14: =IF(LARGE('Client Summary'!$N$2:$N$607,3)<=0,"",INDEX('Client Summary'!$K$2:$K$607,MATCH(LARGE('Client Summary'!$N$2:$N$607,3),'Client Summary'!$N$2:$N$607,0))) -> 0 | G14: =IF(LARGE('Client Summary'!$N$2:$N$607,3)<=0,"",INDEX('Client Summary'!$L$2:$L$607,MATCH(LARGE('Client Summary'!$N$2:$N$607,3),'Client Summary'!$N$2:$N$607,0))) -> 0 | H14: =IF(LARGE('Client Summary'!$N$2:$N$607,3)<=0,"",INDEX('Client Summary'!$M$2:$M$607,MATCH(LARGE('Client Summary'!$N$2:$N$607,3),'Client Summary'!$N$2:$N$607,0)))
B15: UPCOMING | C15: =SUMPRODUCT(('Pending RQ Deadlines'!$J$2:$J$1271="UPCOMING")*('Pending RQ Deadlines'!$K$2:$K$1271="Yes")) -> 467 | E15: =IF(LARGE('Client Summary'!$N$2:$N$607,4)<=0,"",INDEX('Client Summary'!$A$2:$A$607,MATCH(LARGE('Client Summary'!$N$2:$N$607,4),'Client Summary'!$N$2:$N$607,0))) -> ADLER POLLOCK & SHEEHAN P.C. | F15: =IF(LARGE('Client Summary'!$N$2:$N$607,4)<=0,"",INDEX('Client Summary'!$K$2:$K$607,MATCH(LARGE('Client Summary'!$N$2:$N$607,4),'Client Summary'!$N$2:$N$607,0))) -> 0 | G15: =IF(LARGE('Client Summary'!$N$2:$N$607,4)<=0,"",INDEX('Client Summary'!$L$2:$L$607,MATCH(LARGE('Client Summary'!$N$2:$N$607,4),'Client Summary'!$N$2:$N$607,0))) -> 0 | H15: =IF(LARGE('Client Summary'!$N$2:$N$607,4)<=0,"",INDEX('Client Summary'!$M$2:$M$607,MATCH(LARGE('Client Summary'!$N$2:$N$607,4),'Client Summary'!$N$2:$N$607,0)))
E16: =IF(LARGE('Client Summary'!$N$2:$N$607,5)<=0,"",INDEX('Client Summary'!$A$2:$A$607,MATCH(LARGE('Client Summary'!$N$2:$N$607,5),'Client Summary'!$N$2:$N$607,0))) -> ZENITH PATENT & LAW FIRM | F16: =IF(LARGE('Client Summary'!$N$2:$N$607,5)<=0,"",INDEX('Client Summary'!$K$2:$K$607,MATCH(LARGE('Client Summary'!$N$2:$N$607,5),'Client Summary'!$N$2:$N$607,0))) -> 0 | G16: =IF(LARGE('Client Summary'!$N$2:$N$607,5)<=0,"",INDEX('Client Summary'!$L$2:$L$607,MATCH(LARGE('Client Summary'!$N$2:$N$607,5),'Client Summary'!$N$2:$N$607,0))) -> 0 | H16: =IF(LARGE('Client Summary'!$N$2:$N$607,5)<=0,"",INDEX('Client Summary'!$M$2:$M$607,MATCH(LARGE('Client Summary'!$N$2:$N$607,5),'Client Summary'!$N$2:$N$607,0)))
E17: =IF(LARGE('Client Summary'!$N$2:$N$607,6)<=0,"",INDEX('Client Summary'!$A$2:$A$607,MATCH(LARGE('Client Summary'!$N$2:$N$607,6),'Client Summary'!$N$2:$N$607,0))) -> AGTEKS ORME VE TEKSTIL | F17: =IF(LARGE('Client Summary'!$N$2:$N$607,6)<=0,"",INDEX('Client Summary'!$K$2:$K$607,MATCH(LARGE('Client Summary'!$N$2:$N$607,6),'Client Summary'!$N$2:$N$607,0))) -> 0 | G17: =IF(LARGE('Client Summary'!$N$2:$N$607,6)<=0,"",INDEX('Client Summary'!$L$2:$L$607,MATCH(LARGE('Client Summary'!$N$2:$N$607,6),'Client Summary'!$N$2:$N$607,0))) -> 0 | H17: =IF(LARGE('Client Summary'!$N$2:$N$607,6)<=0,"",INDEX('Client Summary'!$M$2:$M$607,MATCH(LARGE('Client Summary'!$N$2:$N$607,6),'Client Summary'!$N$2:$N$607,0)))
E18: =IF(LARGE('Client Summary'!$N$2:$N$607,7)<=0,"",INDEX('Client Summary'!$A$2:$A$607,MATCH(LARGE('Client Summary'!$N$2:$N$607,7),'Client Summary'!$N$2:$N$607,0))) -> AHMEDABAD TEXTILE IND. RESEARCH ASSOCIATION | F18: =IF(LARGE('Client Summary'!$N$2:$N$607,7)<=0,"",INDEX('Client Summary'!$K$2:$K$607,MATCH(LARGE('Client Summary'!$N$2:$N$607,7),'Client Summary'!$N$2:$N$607,0))) -> 1 | G18: =IF(LARGE('Client Summary'!$N$2:$N$607,7)<=0,"",INDEX('Client Summary'!$L$2:$L$607,MATCH(LARGE('Client Summary'!$N$2:$N$607,7),'Client Summary'!$N$2:$N$607,0))) -> 1 | H18: =IF(LARGE('Client Summary'!$N$2:$N$607,7)<=0,"",INDEX('Client Summary'!$M$2:$M$607,MATCH(LARGE('Client Summary'!$N$2:$N$607,7),'Client Summary'!$N$2:$N$607,0)))
E19: =IF(LARGE('Client Summary'!$N$2:$N$607,8)<=0,"",INDEX('Client Summary'!$A$2:$A$607,MATCH(LARGE('Client Summary'!$N$2:$N$607,8),'Client Summary'!$N$2:$N$607,0))) -> AIG HOSPITALS | F19: =IF(LARGE('Client Summary'!$N$2:$N$607,8)<=0,"",INDEX('Client Summary'!$K$2:$K$607,MATCH(LARGE('Client Summary'!$N$2:$N$607,8),'Client Summary'!$N$2:$N$607,0))) -> 1 | G19: =IF(LARGE('Client Summary'!$N$2:$N$607,8)<=0,"",INDEX('Client Summary'!$L$2:$L$607,MATCH(LARGE('Client Summary'!$N$2:$N$607,8),'Client Summary'!$N$2:$N$607,0))) -> 1 | H19: =IF(LARGE('Client Summary'!$N$2:$N$607,8)<=0,"",INDEX('Client Summary'!$M$2:$M$607,MATCH(LARGE('Client Summary'!$N$2:$N$607,8),'Client Summary'!$N$2:$N$607,0)))
E20: =IF(LARGE('Client Summary'!$N$2:$N$607,9)<=0,"",INDEX('Client Summary'!$A$2:$A$607,MATCH(LARGE('Client Summary'!$N$2:$N$607,9),'Client Summary'!$N$2:$N$607,0))) -> AISIN CORPORATION | F20: =IF(LARGE('Client Summary'!$N$2:$N$607,9)<=0,"",INDEX('Client Summary'!$K$2:$K$607,MATCH(LARGE('Client Summary'!$N$2:$N$607,9),'Client Summary'!$N$2:$N$607,0))) -> 1 | G20: =IF(LARGE('Client Summary'!$N$2:$N$607,9)<=0,"",INDEX('Client Summary'!$L$2:$L$607,MATCH(LARGE('Client Summary'!$N$2:$N$607,9),'Client Summary'!$N$2:$N$607,0))) -> 1 | H20: =IF(LARGE('Client Summary'!$N$2:$N$607,9)<=0,"",INDEX('Client Summary'!$M$2:$M$607,MATCH(LARGE('Client Summary'!$N$2:$N$607,9),'Client Summary'!$N$2:$N$607,0)))
E21: =IF(LARGE('Client Summary'!$N$2:$N$607,10)<=0,"",INDEX('Client Summary'!$A$2:$A$607,MATCH(LARGE('Client Summary'!$N$2:$N$607,10),'Client Summary'!$N$2:$N$607,0))) -> YOKOHAMA SIGMA IP LAW FIRM | F21: =IF(LARGE('Client Summary'!$N$2:$N$607,10)<=0,"",INDEX('Client Summary'!$K$2:$K$607,MATCH(LARGE('Client Summary'!$N$2:$N$607,10),'Client Summary'!$N$2:$N$607,0))) -> 0 | G21: =IF(LARGE('Client Summary'!$N$2:$N$607,10)<=0,"",INDEX('Client Summary'!$L$2:$L$607,MATCH(LARGE('Client Summary'!$N$2:$N$607,10),'Client Summary'!$N$2:$N$607,0))) -> 0 | H21: =IF(LARGE('Client Summary'!$N$2:$N$607,10)<=0,"",INDEX('Client Summary'!$M$2:$M$607,MATCH(LARGE('Client Summary'!$N$2:$N$607,10),'Client Summary'!$N$2:$N$607,0)))
B22: Notes:
B23: • RQ (Request for Examination) must be filed within 31 months of the priority/filing date under the Indian Patents Act.
B24: • 'Pending RQ (Active)' excludes cases marked Abandoned / Closed / Merged, where no RQ action is required.
B25: • 'Days Remaining' and urgency flags on the Pending RQ Deadlines sheet use TODAY() and update automatically when reopened.
B26: • Client Summary sheet lists all 606 clients; sort/filter by Overdue RQ or Due within 90 Days to prioritise outreach.

Sheet Client Summary
A1: Client Name | B1: Total Cases | C1: RFE Filed | D1: Provisional Filed | E1: Complete Filed | F1: Application Filed | G1: Under Examination | H1: Granted | I1: Abandoned/Closed/Merged | J1: Pending RQ (Active) | K1: Overdue RQ | L1: Due within 90 Days | M1: Next RQ Due Date | N1: Urgency Score (for ranking)
A2: QUALCOMM INCORPORATED | B2: =COUNTIF(Data!$D$2:$D$6232,A2) -> 907 | C2: =COUNTIFS(Data!$D$2:$D$6232,A2,Data!$R$2:$R$6232,"RFE FILED") -> 808 | D2: =COUNTIFS(Data!$D$2:$D$6232,A2,Data!$R$2:$R$6232,"PROVISIONAL FILED") -> 90 | E2: =COUNTIFS(Data!$D$2:$D$6232,A2,Data!$R$2:$R$6232,"COMPLETE FILED") -> 1 | F2: =COUNTIFS(Data!$D$2:$D$6232,A2,Data!$R$2:$R$6232,"APPLICATION FILED") -> 0 | G2: =COUNTIFS(Data!$D$2:$D$6232,A2,Data!$R$2:$R$6232,"UNDER EXAMINATION") -> 5 | H2: =COUNTIFS(Data!$D$2:$D$6232,A2,Data!$R$2:$R$6232,"GRANTED") -> 0 | I2: =SUMPRODUCT((Data!$D$2:$D$6232=A2)*((Data!$R$2:$R$6232="ABANDONED")+(Data!$R$2:$R$6232="CLOSED")+(Data!$R$2:$R$6232="MERGED"))) -> 2 | J2: =COUNTIFS('Pending RQ Deadlines'!$C$2:$C$1271,A2,'Pending RQ Deadlines'!$K$2:$K$1271,"Yes") -> 91 | K2: =COUNTIFS('Pending RQ Deadlines'!$C$2:$C$1271,A2,'Pending RQ Deadlines'!$J$2:$J$1271,"OVERDUE") -> 62 | L2: =SUMPRODUCT(('Pending RQ Deadlines'!$C$2:$C$1271=A2)*('Pending RQ Deadlines'!$J$2:$J$1271<>"UPCOMING")*('Pending RQ Deadlines'!$K$2:$K$1271="Yes")) -> 62 | M2: =IFERROR(_xludf.minifs('Pending RQ Deadlines'!$G$2:$G$1271,'Pending RQ Deadlines'!$C$2:$C$1271,A2),"") | N2: =ROW()-L2+K2/100 -> -59.38
A3: PHIL & ONZI | B3: =COUNTIF(Data!$D$2:$D$6232,A3) -> 258 | C3: =COUNTIFS(Data!$D$2:$D$6232,A3,Data!$R$2:$R$6232,"RFE FILED") -> 258 | D3: =COUNTIFS(Data!$D$2:$D$6232,A3,Data!$R$2:$R$6232,"PROVISIONAL FILED") -> 0 | E3: =COUNTIFS(Data!$D$2:$D$6232,A3,Data!$R$2:$R$6232,"COMPLETE FILED") -> 0 | F3: =COUNTIFS(Data!$D$2:$D$6232,A3,Data!$R$2:$R$6232,"APPLICATION FILED") -> 0 | G3: =COUNTIFS(Data!$D$2:$D$6232,A3,Data!$R$2:$R$6232,"UNDER EXAMINATION") -> 0 | H3: =COUNTIFS(Data!$D$2:$D$6232,A3,Data!$R$2:$R$6232,"GRANTED") -> 0 | I3: =SUMPRODUCT((Data!$D$2:$D$6232=A3)*((Data!$R$2:$R$6232="ABANDONED")+(Data!$R$2:$R$6232="CLOSED")+(Data!$R$2:$R$6232="MERGED"))) -> 0 | J3: =COUNTIFS('Pending RQ Deadlines'!$C$2:$C$1271,A3,'Pending RQ Deadlines'!$K$2:$K$1271,"Yes") -> 0 | K3: =COUNTIFS('Pending RQ Deadlines'!$C$2:$C$1271,A3,'Pending RQ Deadlines'!$J$2:$J$1271,"OVERDUE") -> 0 | L3: =SUMPRODUCT(('Pending RQ Deadlines'!$C$2:$C$1271=A3)*('Pending RQ Deadlines'!$J$2:$J$1271<>"UPCOMING")*('Pending RQ Deadlines'!$K$2:$K$1271="Yes")) -> 0 | M3: =IFERROR(_xludf.minifs('Pending RQ Deadlines'!$G$2:$G$1271,'Pending RQ Deadlines'!$C$2:$C$1271,A3),"") | N3: =ROW()-L3+K3/100 -> 3
A4: Samsung R&D Institute India-Bangalore Pvt. Ltd. | B4: =COUNTIF(Data!$D$2:$D$6232,A4) -> 185 | C4: =COUNTIFS(Data!$D$2:$D$6232,A4,Data!$R$2:$R$6232,"RFE FILED") -> 65 | D4: =COUNTIFS(Data!$D$2:$D$6232,A4,Data!$R$2:$R$6232,"PROVISIONAL FILED") -> 117 | E4: =COUNTIFS(Data!$D$2:$D$6232,A4,Data!$R$2:$R$6232,"COMPLETE FILED") -> 0 | F4: =COUNTIFS(Data!$D$2:$D$6232,A4,Data!$R$2:$R$6232,"APPLICATION FILED") -> 0 | G4: =COUNTIFS(Data!$D$2:$D$6232,A4,Data!$R$2:$R$6232,"UNDER EXAMINATION") -> 0 | H4: =COUNTIFS(Data!$D$2:$D$6232,A4,Data!$R$2:$R$6232,"GRANTED") -> 0 | I4: =SUMPRODUCT((Data!$D$2:$D$6232=A4)*((Data!$R$2:$R$6232="ABANDONED")+(Data!$R$2:$R$6232="CLOSED")+(Data!$R$2:$R$6232="MERGED"))) -> 3 | J4: =COUNTIFS('Pending RQ Deadlines'!$C$2:$C$1271,A4,'Pending RQ Deadlines'!$K$2:$K$1271,"Yes") -> 117 | K4: =COUNTIFS('Pending RQ Deadlines'!$C$2:$C$1271,A4,'Pending RQ Deadlines'!$J$2:$J$1271,"OVERDUE") -> 76 | L4: =SUMPRODUCT(('Pending RQ Deadlines'!$C$2:$C$1271=A4)*('Pending RQ Deadlines'!$J$2:$J$1271<>"UPCOMING")*('Pending RQ Deadlines'!$K$2:$K$1271="Yes")) -> 74 | M4: =IFERROR(_xludf.minifs('Pending RQ Deadlines'!$G$2:$G$1271,'Pending RQ Deadlines'!$C$2:$C$1271,A4),"") | N4: =ROW()-L4+K4/100 -> -69.24
A5: BAE, KIM & LEE IP GROUP | B5: =COUNTIF(Data!$D$2:$D$6232,A5) -> 184 | C5: =COUNTIFS(Data!$D$2:$D$6232,A5,Data!$R$2:$R$6232,"RFE FILED") -> 184 | D5: =COUNTIFS(Data!$D$2:$D$6232,A5,Data!$R$2:$R$6232,"PROVISIONAL FILED") -> 0 | E5: =COUNTIFS(Data!$D$2:$D$6232,A5,Data!$R$2:$R$6232,"COMPLETE FILED") -> 0 | F5: =COUNTIFS(Data!$D$2:$D$6232,A5,Data!$R$2:$R$6232,"APPLICATION FILED") -> 0 | G5: =COUNTIFS(Data!$D$2:$D$6232,A5,Data!$R$2:$R$6232,"UNDER EXAMINATION") -> 0 | H5: =COUNTIFS(Data!$D$2:$D$6232,A5,Data!$R$2:$R$6232,"GRANTED") -> 0 | I5: =SUMPRODUCT((Data!$D$2:$D$6232=A5)*((Data!$R$2:$R$6232="ABANDONED")+(Data!$R$2:$R$6232="CLOSED")+(Data!$R$2:$R$6232="MERGED"))) -> 0 | J5: =COUNTIFS('Pending RQ Deadlines'!$C$2:$C$1271,A5,'Pending RQ Deadlines'!$K$2:$K$1271,"Yes") -> 0 | K5: =COUNTIFS('Pending RQ Deadlines'!$C$2:$C$1271,A5,'Pending RQ Deadlines'!$J$2:$J$1271,"OVERDUE") -> 0 | L5: =SUMPRODUCT(('Pending RQ Deadlines'!$C$2:$C$1271=A5)*('Pending RQ Deadlines'!$J$2:$J$1271<>"UPCOMING")*('Pending RQ Deadlines'!$K$2:$K$1271="Yes")) -> 0 | M5: =IFERROR(_xludf.minifs('Pending RQ Deadlines'!$G$2:$G$1271,'Pending RQ Deadlines'!$C$2:$C$1271,A5),"") | N5: =ROW()-L5+K5/100 -> 5
A6: CISCO TECHNOLOGY, INC. | B6: =COUNTIF(Data!$D$2:$D$6232,A6) -> 161 | C6: =COUNTIFS(Data!$D$2:$D$6232,A6,Data!$R$2:$R$6232,"RFE FILED") -> 120 | D6: =COUNTIFS(Data!$D$2:$D$6232,A6,Data!$R$2:$R$6232,"PROVISIONAL FILED") -> 37 | E6: =COUNTIFS(Data!$D$2:$D$6232,A6,Data!$R$2:$R$6232,"COMPLETE FILED") -> 0 | F6: =COUNTIFS(Data!$D$2:$D$6232,A6,Data!$R$2:$R$6232,"APPLICATION FILED") -> 0 | G6: =COUNTIFS(Data!$D$2:$D$6232,A6,Data!$R$2:$R$6232,"UNDER EXAMINATION") -> 1 | H6: =COUNTIFS(Data!$D$2:$D$6232,A6,Data!$R$2:$R$6232,"GRANTED") -> 0 | I6: =SUMPRODUCT((Data!$D$2:$D$6232=A6)*((Data!$R$2:$R$6232="ABANDONED")+(Data!$R$2:$R$6232="CLOSED")+(Data!$R$2:$R$6232="MERGED"))) -> 3 | J6: =COUNTIFS('Pending RQ Deadlines'!$C$2:$C$1271,A6,'Pending RQ Deadlines'!$K$2:$K$1271,"Yes") -> 37 | K6: =COUNTIFS('Pending RQ Deadlines'!$C$2:$C$1271,A6,'Pending RQ Deadlines'!$J$2:$J$1271,"OVERDUE") -> 27 | L6: =SUMPRODUCT(('Pending RQ Deadlines'!$C$2:$C$1271=A6)*('Pending RQ Deadlines'!$J$2:$J$1271<>"UPCOMING")*('Pending RQ Deadlines'!$K$2:$K$1271="Yes")) -> 26 | M6: =IFERROR(_xludf.minifs('Pending RQ Deadlines'!$G$2:$G$1271,'Pending RQ Deadlines'!$C$2:$C$1271,A6),"") | N6: =ROW()-L6+K6/100 -> -19.73
A7: IBM CORPORATION | B7: =COUNTIF(Data!$D$2:$D$6232,A7) -> 136 | C7: =COUNTIFS(Data!$D$2:$D$6232,A7,Data!$R$2:$R$6232,"RFE FILED") -> 129 | D7: =COUNTIFS(Data!$D$2:$D$6232,A7,Data!$R$2:$R$6232,"PROVISIONAL FILED") -> 0 | E7: =COUNTIFS(Data!$D$2:$D$6232,A7,Data!$R$2:$R$6232,"COMPLETE FILED") -> 0 | F7: =COUNTIFS(Data!$D$2:$D$6232,A7,Data!$R$2:$R$6232,"APPLICATION FILED") -> 0 | G7: =COUNTIFS(Data!$D$2:$D$6232,A7,Data!$R$2:$R$6232,"UNDER EXAMINATION") -> 5 | H7: =COUNTIFS(Data!$D$2:$D$6232,A7,Data!$R$2:$R$6232,"GRANTED") -> 0 | I7: =SUMPRODUCT((Data!$D$2:$D$6232=A7)*((Data!$R$2:$R$6232="ABANDONED")+(Data!$R$2:$R$6232="CLOSED")+(Data!$R$2:$R$6232="MERGED"))) -> 0 | J7: =COUNTIFS('Pending RQ Deadlines'!$C$2:$C$1271,A7,'Pending RQ Deadlines'!$K$2:$K$1271,"Yes") -> 0 | K7: =COUNTIFS('Pending RQ Deadlines'!$C$2:$C$1271,A7,'Pending RQ Deadlines'!$J$2:$J$1271,"OVERDUE") -> 0 | L7: =SUMPRODUCT(('Pending RQ Deadlines'!$C$2:$C$1271=A7)*('Pending RQ Deadlines'!$J$2:$J$1271<>"UPCOMING")*('Pending RQ Deadlines'!$K$2:$K$1271="Yes")) -> 0 | M7: =IFERROR(_xludf.minifs('Pending RQ Deadlines'!$G$2:$G$1271,'Pending RQ Deadlines'!$C$2:$C$1271,A7),"") | N7: =ROW()-L7+K7/100 -> 7
A8: MERCEDES-BENZ INTELLECTUAL PROPERTY GMBH & CO KG | B8: =COUNTIF(Data!$D$2:$D$6232,A8) -> 135 | C8: =COUNTIFS(Data!$D$2:$D$6232,A8,Data!$R$2:$R$6232,"RFE FILED") -> 0 | D8: =COUNTIFS(Data!$D$2:$D$6232,A8,Data!$R$2:$R$6232,"PROVISIONAL FILED") -> 0 | E8: =COUNTIFS(Data!$D$2:$D$6232,A8,Data!$R$2:$R$6232,"COMPLETE FILED") -> 135 | F8: =COUNTIFS(Data!$D$2:$D$6232,A8,Data!$R$2:$R$6232,"APPLICATION FILED") -> 0 | G8: =COUNTIFS(Data!$D$2:$D$6232,A8,Data!$R$2:$R$6232,"UNDER EXAMINATION") -> 0 | H8: =COUNTIFS(Data!$D$2:$D$6232,A8,Data!$R$2:$R$6232,"GRANTED") -> 0 | I8: =SUMPRODUCT((Data!$D$2:$D$6232=A8)*((Data!$R$2:$R$6232="ABANDONED")+(Data!$R$2:$R$6232="CLOSED")+(Data!$R$2:$R$6232="MERGED"))) -> 0 | J8: =COUNTIFS('Pending RQ Deadlines'!$C$2:$C$1271,A8,'Pending RQ Deadlines'!$K$2:$K$1271,"Yes") -> 135 | K8: =COUNTIFS('Pending RQ Deadlines'!$C$2:$C$1271,A8,'Pending RQ Deadlines'!$J$2:$J$1271,"OVERDUE") -> 93 | L8: =SUMPRODUCT(('Pending RQ Deadlines'!$C$2:$C$1271=A8)*('Pending RQ Deadlines'!$J$2:$J$1271<>"UPCOMING")*('Pending RQ Deadlines'!$K$2:$K$1271="Yes")) -> 93 | M8: =IFERROR(_xludf.minifs('Pending RQ Deadlines'!$G$2:$G$1271,'Pending RQ Deadlines'!$C$2:$C$1271,A8),"") | N8: =ROW()-L8+K8/100 -> -84.07
A9: TATA STEEL LIMITED | B9: =COUNTIF(Data!$D$2:$D$6232,A9) -> 134 | C9: =COUNTIFS(Data!$D$2:$D$6232,A9,Data!$R$2:$R$6232,"RFE FILED") -> 134 | D9: =COUNTIFS(Data!$D$2:$D$6232,A9,Data!$R$2:$R$6232,"PROVISIONAL FILED") -> 0 | E9: =COUNTIFS(Data!$D$2:$D$6232,A9,Data!$R$2:$R$6232,"COMPLETE FILED") -> 0 | F9: =COUNTIFS(Data!$D$2:$D$6232,A9,Data!$R$2:$R$6232,"APPLICATION FILED") -> 0 | G9: =COUNTIFS(Data!$D$2:$D$6232,A9,Data!$R$2:$R$6232,"UNDER EXAMINATION") -> 0 | H9: =COUNTIFS(Data!$D$2:$D$6232,A9,Data!$R$2:$R$6232,"GRANTED") -> 0 | I9: =SUMPRODUCT((Data!$D$2:$D$6232=A9)*((Data!$R$2:$R$6232="ABANDONED")+(Data!$R$2:$R$6232="CLOSED")+(Data!$R$2:$R$6232="MERGED"))) -> 0 | J9: =COUNTIFS('Pending RQ Deadlines'!$C$2:$C$1271,A9,'Pending RQ Deadlines'!$K$2:$K$1271,"Yes") -> 0 | K9: =COUNTIFS('Pending RQ Deadlines'!$C$2:$C$1271,A9,'Pending RQ Deadlines'!$J$2:$J$1271,"OVERDUE") -> 0 | L9: =SUMPRODUCT(('Pending RQ Deadlines'!$C$2:$C$1271=A9)*('Pending RQ Deadlines'!$J$2:$J$1271<>"UPCOMING")*('Pending RQ Deadlines'!$K$2:$K$1271="Yes")) -> 0 | M9: =IFERROR(_xludf.minifs('Pending RQ Deadlines'!$G$2:$G$1271,'Pending RQ Deadlines'!$C$2:$C$1271,A9),"") | N9: =ROW()-L9+K9/100 -> 9
A10: ABB SWITZERLAND LTD. | B10: =COUNTIF(Data!$D$2:$D$6232,A10) -> 127 | C10: =COUNTIFS(Data!$D$2:$D$6232,A10,Data!$R$2:$R$6232,"RFE FILED") -> 124 | D10: =COUNTIFS(Data!$D$2:$D$6232,A10,Data!$R$2:$R$6232,"PROVISIONAL FILED") -> 2 | E10: =COUNTIFS(Data!$D$2:$D$6232,A10,Data!$R$2:$R$6232,"COMPLETE FILED") -> 0 | F10: =COUNTIFS(Data!$D$2:$D$6232,A10,Data!$R$2:$R$6232,"APPLICATION FILED") -> 0 | G10: =COUNTIFS(Data!$D$2:$D$6232,A10,Data!$R$2:$R$6232,"UNDER EXAMINATION") -> 0 | H10: =COUNTIFS(Data!$D$2:$D$6232,A10,Data!$R$2:$R$6232,"GRANTED") -> 0 | I10: =SUMPRODUCT((Data!$D$2:$D$6232=A10)*((Data!$R$2:$R$6232="ABANDONED")+(Data!$R$2:$R$6232="CLOSED")+(Data!$R$2:$R$6232="MERGED"))) -> 0 | J10: =COUNTIFS('Pending RQ Deadlines'!$C$2:$C$1271,A10,'Pending RQ Deadlines'!$K$2:$K$1271,"Yes") -> 3 | K10: =COUNTIFS('Pending RQ Deadlines'!$C$2:$C$1271,A10,'Pending RQ Deadlines'!$J$2:$J$1271,"OVERDUE") -> 0 | L10: =SUMPRODUCT(('Pending RQ Deadlines'!$C$2:$C$1271=A10)*('Pending RQ Deadlines'!$J$2:$J$1271<>"UPCOMING")*('Pending RQ Deadlines'!$K$2:$K$1271="Yes")) -> 0 | M10: =IFERROR(_xludf.minifs('Pending RQ Deadlines'!$G$2:$G$1271,'Pending RQ Deadlines'!$C$2:$C$1271,A10),"") | N10: =ROW()-L10+K10/100 -> 10
A11: FOLEY & LARDNER LLP | B11: =COUNTIF(Data!$D$2:$D$6232,A11) -> 111 | C11: =COUNTIFS(Data!$D$2:$D$6232,A11,Data!$R$2:$R$6232,"RFE FILED") -> 63 | D11: =COUNTIFS(Data!$D$2:$D$6232,A11,Data!$R$2:$R$6232,"PROVISIONAL FILED") -> 36 | E11: =COUNTIFS(Data!$D$2:$D$6232,A11,Data!$R$2:$R$6232,"COMPLETE FILED") -> 5 | F11: =COUNTIFS(Data!$D$2:$D$6232,A11,Data!$R$2:$R$6232,"APPLICATION FILED") -> 3 | G11: =COUNTIFS(Data!$D$2:$D$6232,A11,Data!$R$2:$R$6232,"UNDER EXAMINATION") -> 0 | H11: =COUNTIFS(Data!$D$2:$D$6232,A11,Data!$R$2:$R$6232,"GRANTED") -> 0 | I11: =SUMPRODUCT((Data!$D$2:$D$6232=A11)*((Data!$R$2:$R$6232="ABANDONED")+(Data!$R$2:$R$6232="CLOSED")+(Data!$R$2:$R$6232="MERGED"))) -> 3 | J11: =COUNTIFS('Pending RQ Deadlines'!$C$2:$C$1271,A11,'Pending RQ Deadlines'!$K$2:$K$1271,"Yes") -> 44 | K11: =COUNTIFS('Pending RQ Deadlines'!$C$2:$C$1271,A11,'Pending RQ Deadlines'!$J$2:$J$1271,"OVERDUE") -> 32 | L11: =SUMPRODUCT(('Pending RQ Deadlines'!$C$2:$C$1271=A11)*('Pending RQ Deadlines'!$J$2:$J$1271<>"UPCOMING")*('Pending RQ Deadlines'!$K$2:$K$1271="Yes")) -> 30 | M11: =IFERROR(_xludf.minifs('Pending RQ Deadlines'!$G$2:$G$1271,'Pending RQ Deadlines'!$C$2:$C$1271,A11),"") | N11: =ROW()-L11+K11/100 -> -18.68
A12: TATA MOTORS PASSENGER VEHICLES LIMITED | B12: =COUNTIF(Data!$D$2:$D$6232,A12) -> 93 | C12: =COUNTIFS(Data!$D$2:$D$6232,A12,Data!$R$2:$R$6232,"RFE FILED") -> 83 | D12: =COUNTIFS(Data!$D$2:$D$6232,A12,Data!$R$2:$R$6232,"PROVISIONAL FILED") -> 10 | E12: =COUNTIFS(Data!$D$2:$D$6232,A12,Data!$R$2:$R$6232,"COMPLETE FILED") -> 0 | F12: =COUNTIFS(Data!$D$2:$D$6232,A12,Data!$R$2:$R$6232,"APPLICATION FILED") -> 0 | G12: =COUNTIFS(Data!$D$2:$D$6232,A12,Data!$R$2:$R$6232,"UNDER EXAMINATION") -> 0 | H12: =COUNTIFS(Data!$D$2:$D$6232,A12,Data!$R$2:$R$6232,"GRANTED") -> 0 | I12: =SUMPRODUCT((Data!$D$2:$D$6232=A12)*((Data!$R$2:$R$6232="ABANDONED")+(Data!$R$2:$R$6232="CLOSED")+(Data!$R$2:$R$6232="MERGED"))) -> 0 | J12: =COUNTIFS('Pending RQ Deadlines'!$C$2:$C$1271,A12,'Pending RQ Deadlines'!$K$2:$K$1271,"Yes") -> 10 | K12: =COUNTIFS('Pending RQ Deadlines'!$C$2:$C$1271,A12,'Pending RQ Deadlines'!$J$2:$J$1271,"OVERDUE") -> 2 | L12: =SUMPRODUCT(('Pending RQ Deadlines'!$C$2:$C$1271=A12)*('Pending RQ Deadlines'!$J$2:$J$1271<>"UPCOMING")*('Pending RQ Deadlines'!$K$2:$K$1271="Yes")) -> 3 | M12: =IFERROR(_xludf.minifs('Pending RQ Deadlines'!$G$2:$G$1271,'Pending RQ Deadlines'!$C$2:$C$1271,A12),"") | N12: =ROW()-L12+K12/100 -> 9.02
A13: RAKUTEN MOBILE INC | B13: =COUNTIF(Data!$D$2:$D$6232,A13) -> 92 | C13: =COUNTIFS(Data!$D$2:$D$6232,A13,Data!$R$2:$R$6232,"RFE FILED") -> 0 | D13: =COUNTIFS(Data!$D$2:$D$6232,A13,Data!$R$2:$R$6232,"PROVISIONAL FILED") -> 57 | E13: =COUNTIFS(Data!$D$2:$D$6232,A13,Data!$R$2:$R$6232,"COMPLETE FILED") -> 33 | F13: =COUNTIFS(Data!$D$2:$D$6232,A13,Data!$R$2:$R$6232,"APPLICATION FILED") -> 0 | G13: =COUNTIFS(Data!$D$2:$D$6232,A13,Data!$R$2:$R$6232,"UNDER EXAMINATION") -> 0 | H13: =COUNTIFS(Data!$D$2:$D$6232,A13,Data!$R$2:$R$6232,"GRANTED") -> 0 | I13: =SUMPRODUCT((Data!$D$2:$D$6232=A13)*((Data!$R$2:$R$6232="ABANDONED")+(Data!$R$2:$R$6232="CLOSED")+(Data!$R$2:$R$6232="MERGED"))) -> 2 | J13: =COUNTIFS('Pending RQ Deadlines'!$C$2:$C$1271,A13,'Pending RQ Deadlines'!$K$2:$K$1271,"Yes") -> 90 | K13: =COUNTIFS('Pending RQ Deadlines'!$C$2:$C$1271,A13,'Pending RQ Deadlines'!$J$2:$J$1271,"OVERDUE") -> 55 | L13: =SUMPRODUCT(('Pending RQ Deadlines'!$C$2:$C$1271=A13)*('Pending RQ Deadlines'!$J$2:$J$1271<>"UPCOMING")*('Pending RQ Deadlines'!$K$2:$K$1271="Yes")) -> 53 | M13: =IFERROR(_xludf.minifs('Pending RQ Deadlines'!$G$2:$G$1271,'Pending RQ Deadlines'!$C$2:$C$1271,A13),"") | N13: =ROW()-L13+K13/100 -> -39.45
... A607: ZUMUTOR BIOLOGICS, INC. | B607: =COUNTIF(Data!$D$2:$D$6232,A607) -> 1 | C607: =COUNTIFS(Data!$D$2:$D$6232,A607,Data!$R$2:$R$6232,"RFE FILED") -> 0 | D607: =COUNTIFS(Data!$D$2:$D$6232,A607,Data!$R$2:$R$6232,"PROVISIONAL FILED") -> 1 | E607: =COUNTIFS(Data!$D$2:$D$6232,A607,Data!$R$2:$R$6232,"COMPLETE FILED") -> 0 | F607: =COUNTIFS(Data!$D$2:$D$6232,A607,Data!$R$2:$R$6232,"APPLICATION FILED") -> 0 | G607: =COUNTIFS(Data!$D$2:$D$6232,A607,Data!$R$2:$R$6232,"UNDER EXAMINATION") -> 0 | H607: =COUNTIFS(Data!$D$2:$D$6232,A607,Data!$R$2:$R$6232,"GRANTED") -> 0 | I607: =SUMPRODUCT((Data!$D$2:$D$6232=A607)*((Data!$R$2:$R$6232="ABANDONED")+(Data!$R$2:$R$6232="CLOSED")+(Data!$R$2:$R$6232="MERGED"))) -> 0 | J607: =COUNTIFS('Pending RQ Deadlines'!$C$2:$C$1271,A607,'Pending RQ Deadlines'!$K$2:$K$1271,"Yes") -> 1 | K607: =COUNTIFS('Pending RQ Deadlines'!$C$2:$C$1271,A607,'Pending RQ Deadlines'!$J$2:$J$1271,"OVERDUE") -> 1 | L607: =SUMPRODUCT(('Pending RQ Deadlines'!$C$2:$C$1271=A607)*('Pending RQ Deadlines'!$J$2:$J$1271<>"UPCOMING")*('Pending RQ Deadlines'!$K$2:$K$1271="Yes")) -> 1 | M607: =IFERROR(_xludf.minifs('Pending RQ Deadlines'!$G$2:$G$1271,'Pending RQ Deadlines'!$C$2:$C$1271,A607),"") | N607: =ROW()-L607+K607/100 -> 606.01

Sheet Pending RQ Deadlines
A1: File No | B1: Application No | C1: Client Name | D1: Client Ref | E1: Status | F1: Filing Date | G1: RQ Due Date | H1: Days Remaining | I1: Months | J1: Urgency | K1: Action Required | L1: Column1 | M1: Column2
A2: IP91209 | B2: 202517111826 | C2: UNION TRANSLATIONS | D2: RECO091725 | E2: ABANDONED | F2: 45976 | G2: =EDATE(DataTable[[#This Row],[Priority Date]],31) -> 46784 | H2: =G2-TODAY() -> 527 | I2: =PendingRQTable[[#This Row],[Days Remaining]]/(365/12) -> 17.326027 | J2: =IF(H2<0,"OVERDUE",IF(H2<=30,"DUE <=30 DAYS",IF(H2<=90,"DUE <=90 DAYS","UPCOMING"))) -> UPCOMING | K2: =IF(E2="ABANDONED","No - Case Inactive","Yes") -> No - Case Inactive
A3: IP95031 | B3: 202617071212 | C3: SHENTALENT IP AGENCY CO LTD | D3: PLEASE PROVIDE | E3: APPLICATION FILED | F3: 46181 | G3: =EDATE(DataTable[[#This Row],[Priority Date]],31) -> 46784 | H3: =G3-TODAY() -> 527 | I3: =PendingRQTable[[#This Row],[Days Remaining]]/(365/12) -> 17.326027 | J3: =IF(H3<0,"OVERDUE",IF(H3<=30,"DUE <=30 DAYS",IF(H3<=90,"DUE <=90 DAYS","UPCOMING"))) -> UPCOMING | K3: =IF(E3="APPLICATION FILED","Yes","Yes") -> Yes
A4: IP93547 | B4: 202618014544 | C4: DINSMORE & SHOHL LLP | D4: PLEASE PROVIDE | E4: APPLICATION FILED | F4: 46063 | G4: =EDATE(DataTable[[#This Row],[Priority Date]],31) -> 46430 | H4: =G4-TODAY() -> 173 | I4: =PendingRQTable[[#This Row],[Days Remaining]]/(365/12) -> 5.6876712 | J4: =IF(H4<0,"OVERDUE",IF(H4<=30,"DUE <=30 DAYS",IF(H4<=90,"DUE <=90 DAYS","UPCOMING"))) -> UPCOMING | K4: =IF(E4="APPLICATION FILED","Yes","Yes") -> Yes
A5: IP89647 | B5: 202517096982 | C5: APPLEYARD LEES | D5: P45661INN1 | E5: APPLICATION FILED | F5: 45938 | G5: =EDATE(DataTable[[#This Row],[Priority Date]],31) -> 46221 | H5: =G5-TODAY() -> -36 | I5: =PendingRQTable[[#This Row],[Days Remaining]]/(365/12) -> -1.1835616 | J5: =IF(H5<0,"OVERDUE",IF(H5<=30,"DUE <=30 DAYS",IF(H5<=90,"DUE <=90 DAYS","UPCOMING"))) -> OVERDUE | K5: =IF(E5="APPLICATION FILED","Yes","Yes") -> Yes
A6: IP94313 | B6: 202648032709 | C6: SHEPPARD MULLIN RICHTER & HAMPTON LLP | D6: 67JG-335587-IN2 | E6: APPLICATION FILED | F6: 46099 | G6: =EDATE(DataTable[[#This Row],[Priority Date]],31) -> 45859 | H6: =G6-TODAY() -> -398 | I6: =PendingRQTable[[#This Row],[Days Remaining]]/(365/12) -> -13.084932 | J6: =IF(H6<0,"OVERDUE",IF(H6<=30,"DUE <=30 DAYS",IF(H6<=90,"DUE <=90 DAYS","UPCOMING"))) -> OVERDUE | K6: =IF(E6="APPLICATION FILED","Yes","Yes") -> Yes
A7: IP94365 | B7: 202618032821 | C7: BOEHMERT & BOEHMERT | D7: P11625WOIN-A | E7: APPLICATION FILED | F7: 46099 | G7: =EDATE(DataTable[[#This Row],[Priority Date]],31) -> 46419 | H7: =G7-TODAY() -> 162 | I7: =PendingRQTable[[#This Row],[Days Remaining]]/(365/12) -> 5.3260274 | J7: =IF(H7<0,"OVERDUE",IF(H7<=30,"DUE <=30 DAYS",IF(H7<=90,"DUE <=90 DAYS","UPCOMING"))) -> UPCOMING | K7: =IF(E7="APPLICATION FILED","Yes","Yes") -> Yes
A8: IP91023 | B8: 202547100848 | C8: APPLEYARD LEES | D8: P46226INN1 | E8: APPLICATION FILED | F8: 45947 | G8: =EDATE(DataTable[[#This Row],[Priority Date]],31) -> 46784 | H8: =G8-TODAY() -> 527 | I8: =PendingRQTable[[#This Row],[Days Remaining]]/(365/12) -> 17.326027 | J8: =IF(H8<0,"OVERDUE",IF(H8<=30,"DUE <=30 DAYS",IF(H8<=90,"DUE <=90 DAYS","UPCOMING"))) -> UPCOMING | K8: =IF(E8="APPLICATION FILED","Yes","Yes") -> Yes
A9: IP88699 | B9: 202517105776 | C9: KORYO IP & LAW | D9: LO-340348-PCTIN | E9: APPLICATION FILED | F9: 45962 | G9: =EDATE(DataTable[[#This Row],[Priority Date]],31) -> 46784 | H9: =G9-TODAY() -> 527 | I9: =PendingRQTable[[#This Row],[Days Remaining]]/(365/12) -> 17.326027 | J9: =IF(H9<0,"OVERDUE",IF(H9<=30,"DUE <=30 DAYS",IF(H9<=90,"DUE <=90 DAYS","UPCOMING"))) -> UPCOMING | K9: =IF(E9="APPLICATION FILED","Yes","Yes") -> Yes
A10: IP95417 | B10: 202618059571 | C10: ELI LILLY AND COMPANY | D10: X22015D_IN | E10: APPLICATION FILED | F10: 46153 | G10: =EDATE(DataTable[[#This Row],[Priority Date]],31) -> 45908 | H10: =G10-TODAY() -> -349 | I10: =PendingRQTable[[#This Row],[Days Remaining]]/(365/12) -> -11.473973 | J10: =IF(H10<0,"OVERDUE",IF(H10<=30,"DUE <=30 DAYS",IF(H10<=90,"DUE <=90 DAYS","UPCOMING"))) -> OVERDUE | K10: =IF(E10="APPLICATION FILED","Yes","Yes") -> Yes
A11: IP95787 | B11: 202648064836 | C11: SHENTALENT IP AGENCY CO LTD | D11: OP0021-IN-0621D1 | E11: APPLICATION FILED | F11: 46164 | G11: =EDATE(DataTable[[#This Row],[Priority Date]],31) -> 46784 | H11: =G11-TODAY() -> 527 | I11: =PendingRQTable[[#This Row],[Days Remaining]]/(365/12) -> 17.326027 | J11: =IF(H11<0,"OVERDUE",IF(H11<=30,"DUE <=30 DAYS",IF(H11<=90,"DUE <=90 DAYS","UPCOMING"))) -> UPCOMING | K11: =IF(E11="APPLICATION FILED","Yes","Yes") -> Yes
A12: IP89133 | B12: 202517099711 | C12: HAYNES AND BOONE LLP | D12: 60776.7IN01 | E12: APPLICATION FILED | F12: 45945 | G12: =EDATE(DataTable[[#This Row],[Priority Date]],31) -> 45910 | H12: =G12-TODAY() -> -347 | I12: =PendingRQTable[[#This Row],[Days Remaining]]/(365/12) -> -11.408219 | J12: =IF(H12<0,"OVERDUE",IF(H12<=30,"DUE <=30 DAYS",IF(H12<=90,"DUE <=90 DAYS","UPCOMING"))) -> OVERDUE | K12: =IF(E12="APPLICATION FILED","Yes","Yes") -> Yes
A13: IP92816 | B13: 202647014479 | C13: APPLEYARD LEES | D13: P46440INN1 | E13: APPLICATION FILED | F13: 46063 | G13: =EDATE(DataTable[[#This Row],[Priority Date]],31) -> 45840 | H13: =G13-TODAY() -> -417 | I13: =PendingRQTable[[#This Row],[Days Remaining]]/(365/12) -> -13.709589 | J13: =IF(H13<0,"OVERDUE",IF(H13<=30,"DUE <=30 DAYS",IF(H13<=90,"DUE <=90 DAYS","UPCOMING"))) -> OVERDUE | K13: =IF(E13="APPLICATION FILED","Yes","Yes") -> Yes
A14: IP85682 | B14: 202544062757 | C14: KASAN IP & LAW FIRM | D14: SMP230511IN | E14: APPLICATION FILED | F14: 45839 | G14: =EDATE(DataTable[[#This Row],[Priority Date]],31) -> 46784 | H14: =G14-TODAY() -> 527 | I14: =PendingRQTable[[#This Row],[Days Remaining]]/(365/12) -> 17.326027 | J14: =IF(H14<0,"OVERDUE",IF(H14<=30,"DUE <=30 DAYS",IF(H14<=90,"DUE <=90 DAYS","UPCOMING"))) -> UPCOMING | K14: =IF(E14="APPLICATION FILED","Yes","Yes") -> Yes
... A110: IP92362 | B110: 202644023642 | C110: KORYO IP & LAW | D110: LO-341819-IN | E110: APPLICATION FILED | F110: 46080 | G110: =EDATE(DataTable[[#This Row],[Priority Date]],31) -> 46790 | H110: =G110-TODAY() -> 533 | I110: =PendingRQTable[[#This Row],[Days Remaining]]/(365/12) -> 17.523288 | J110: =IF(H110<0,"OVERDUE",IF(H110<=30,"DUE <=30 DAYS",IF(H110<=90,"DUE <=90 DAYS","UPCOMING"))) -> UPCOMING | K110: =IF(E110="APPLICATION FILED","Yes","Yes") -> Yes
A111: IP93818 | B111: 202614021569 | C111: ANAQUA SERVICES INC | D111: P49851IN00 | E111: CLOSED | F111: 46077 | G111: =EDATE(DataTable[[#This Row],[Priority Date]],31) -> 46790 | H111: =G111-TODAY() -> 533 | I111: =PendingRQTable[[#This Row],[Days Remaining]]/(365/12) -> 17.523288 | J111: =IF(H111<0,"OVERDUE",IF(H111<=30,"DUE <=30 DAYS",IF(H111<=90,"DUE <=90 DAYS","UPCOMING"))) -> UPCOMING | K111: =IF(E111="CLOSED","No - Case Inactive","Yes") -> No - Case Inactive
A112: IP91334 | B112: 202614021223 | C112: KORYO IP & LAW | D112: LO-341601-IN | E112: APPLICATION FILED | F112: 46076 | G112: =EDATE(DataTable[[#This Row],[Priority Date]],31) -> 45915 | H112: =G112-TODAY() -> -342 | I112: =PendingRQTable[[#This Row],[Days Remaining]]/(365/12) -> -11.243836 | J112: =IF(H112<0,"OVERDUE",IF(H112<=30,"DUE <=30 DAYS",IF(H112<=90,"DUE <=90 DAYS","UPCOMING"))) -> OVERDUE | K112: =IF(E112="APPLICATION FILED","Yes","Yes") -> Yes
A113: IP91099 | B113: 202644025590 | C113: KASAN IP & LAW FIRM | D113: SMP240612IN | E113: APPLICATION FILED | F113: 46085 | G113: =EDATE(DataTable[[#This Row],[Priority Date]],31) -> 46790 | H113: =G113-TODAY() -> 533 | I113: =PendingRQTable[[#This Row],[Days Remaining]]/(365/12) -> 17.523288 | J113: =IF(H113<0,"OVERDUE",IF(H113<=30,"DUE <=30 DAYS",IF(H113<=90,"DUE <=90 DAYS","UPCOMING"))) -> UPCOMING | K113: =IF(E113="APPLICATION FILED","Yes","Yes") -> Yes
A114: IP93422 | B114: 202644013103 | C114: FOLEY & LARDNER LLP | D114: 106389-9730 | E114: APPLICATION FILED | F114: 46059 | G114: =EDATE(DataTable[[#This Row],[Priority Date]],31) -> 45866 | H114: =G114-TODAY() -> -391 | I114: =PendingRQTable[[#This Row],[Days Remaining]]/(365/12) -> -12.854795 | J114: =IF(H114<0,"OVERDUE",IF(H114<=30,"DUE <=30 DAYS",IF(H114<=90,"DUE <=90 DAYS","UPCOMING"))) -> OVERDUE | K114: =IF(E114="APPLICATION FILED","Yes","Yes") -> Yes
A115: IP91436 | B115: 202614011184 | C115: KASAN IP & LAW FIRM | D115: SMP240453IN | E115: APPLICATION FILED | F115: 46056 | G115: =EDATE(DataTable[[#This Row],[Priority Date]],31) -> 46137 | H115: =G115-TODAY() -> -120 | I115: =PendingRQTable[[#This Row],[Days Remaining]]/(365/12) -> -3.9452055 | J115: =IF(H115<0,"OVERDUE",IF(H115<=30,"DUE <=30 DAYS",IF(H115<=90,"DUE <=90 DAYS","UPCOMING"))) -> OVERDUE | K115: =IF(E115="APPLICATION FILED","Yes","Yes") -> Yes
A116: IP91594 | B116: 202644028715 | C116: 21ST CENTURY PATENT & LAW FIRM | D116: HZ3187IN/SB | E116: APPLICATION FILED | F116: 46092 | G116: =EDATE(DataTable[[#This Row],[Priority Date]],31) -> 46790 | H116: =G116-TODAY() -> 533 | I116: =PendingRQTable[[#This Row],[Days Remaining]]/(365/12) -> 17.523288 | J116: =IF(H116<0,"OVERDUE",IF(H116<=30,"DUE <=30 DAYS",IF(H116<=90,"DUE <=90 DAYS","UPCOMING"))) -> UPCOMING | K116: =IF(E116="APPLICATION FILED","Yes","Yes") -> Yes
A117: IP91519 | B117: 202614016094 | C117: KORYO IP & LAW | D117: LO-341014-IN | E117: APPLICATION FILED | F117: 46066 | G117: =EDATE(DataTable[[#This Row],[Priority Date]],31) -> 46790 | H117: =G117-TODAY() -> 533 | I117: =PendingRQTable[[#This Row],[Days Remaining]]/(365/12) -> 17.523288 | J117: =IF(H117<0,"OVERDUE",IF(H117<=30,"DUE <=30 DAYS",IF(H117<=90,"DUE <=90 DAYS","UPCOMING"))) -> UPCOMING | K117: =IF(E117="APPLICATION FILED","Yes","Yes") -> Yes
A118: IP93603 | B118: 202644029356 | C118: GENERAL ELECTRIC | D118: 701474-IN-4 | E118: APPLICATION FILED | F118: 46093 | G118: =EDATE(DataTable[[#This Row],[Priority Date]],31) -> 45848 | H118: =G118-TODAY() -> -409 | I118: =PendingRQTable[[#This Row],[Days Remaining]]/(365/12) -> -13.446575 | J118: =IF(H118<0,"OVERDUE",IF(H118<=30,"DUE <=30 DAYS",IF(H118<=90,"DUE <=90 DAYS","UPCOMING"))) -> OVERDUE | K118: =IF(E118="APPLICATION FILED","Yes","Yes") -> Yes
A119: IP94239 | B119: 202644029409 | C119: K AND L GATES LLP | D119: 7601410.00216-IN | E119: APPLICATION FILED | F119: 46093 | G119: =EDATE(DataTable[[#This Row],[Priority Date]],31) -> 45846 | H119: =G119-TODAY() -> -411 | I119: =PendingRQTable[[#This Row],[Days Remaining]]/(365/12) -> -13.512329 | J119: =IF(H119<0,"OVERDUE",IF(H119<=30,"DUE <=30 DAYS",IF(H119<=90,"DUE <=90 DAYS","UPCOMING"))) -> OVERDUE | K119: =IF(E119="APPLICATION FILED","Yes","Yes") -> Yes
A120: IP93878 | B120: 202614025077 | C120: Fortmann Tegethoff GbR | D120: 31082.20683IN | E120: APPLICATION FILED | F120: 46084 | G120: =EDATE(DataTable[[#This Row],[Priority Date]],31) -> 45858 | H120: =G120-TODAY() -> -399 | I120: =PendingRQTable[[#This Row],[Days Remaining]]/(365/12) -> -13.117808 | J120: =IF(H120<0,"OVERDUE",IF(H120<=30,"DUE <=30 DAYS",IF(H120<=90,"DUE <=90 DAYS","UPCOMING"))) -> OVERDUE | K120: =IF(E120="APPLICATION FILED","Yes","Yes") -> Yes
A121: IP93652 | B121: 202644024995 | C121: GRUNECKER | D121: PA152261IN-GM405903KAF | E121: APPLICATION FILED | F121: 46084 | G121: =EDATE(DataTable[[#This Row],[Priority Date]],31) -> 45857 | H121: =G121-TODAY() -> -400 | I121: =PendingRQTable[[#This Row],[Days Remaining]]/(365/12) -> -13.150685 | J121: =IF(H121<0,"OVERDUE",IF(H121<=30,"DUE <=30 DAYS",IF(H121<=90,"DUE <=90 DAYS","UPCOMING"))) -> OVERDUE | K121: =IF(E121="APPLICATION FILED","Yes","Yes") -> Yes
A122: IP94228 | B122: 202614032773 | C122: Y.P. LEE, MOCK & PARTNERS | D122: SS-81078-IN | E122: APPLICATION FILED | F122: 46099 | G122: =EDATE(DataTable[[#This Row],[Priority Date]],31) -> 46790 | H122: =G122-TODAY() -> 533 | I122: =PendingRQTable[[#This Row],[Days Remaining]]/(365/12) -> 17.523288 | J122: =IF(H122<0,"OVERDUE",IF(H122<=30,"DUE <=30 DAYS",IF(H122<=90,"DUE <=90 DAYS","UPCOMING"))) -> UPCOMING | K122: =IF(E122="APPLICATION FILED","Yes","Yes") -> Yes
A123: IP93664 | B123: 202614033675 | C123: KORYO IP & LAW | D123: LO-350048-IN | E123: APPLICATION FILED | F123: 46101 | G123: =EDATE(DataTable[[#This Row],[Priority Date]],31) -> 45845 | H123: =G123-TODAY() -> -412 | I123: =PendingRQTable[[#This Row],[Days Remaining]]/(365/12) -> -13.545205 | J123: =IF(H123<0,"OVERDUE",IF(H123<=30,"DUE <=30 DAYS",IF(H123<=90,"DUE <=90 DAYS","UPCOMING"))) -> OVERDUE | K123: =IF(E123="APPLICATION FILED","Yes","Yes") -> Yes
... A163: IP96166 | B163: 202614073180 | C163: KOKUSAI ELECTRIC CORPORATION | D163: 1000582IN01 | E163: APPLICATION FILED | F163: 46185 | G163: =EDATE(DataTable[[#This Row],[Priority Date]],31) -> 46097 | H163: =G163-TODAY() -> -160 | I163: =PendingRQTable[[#This Row],[Days Remaining]]/(365/12) -> -5.260274 | J163: =IF(H163<0,"OVERDUE",IF(H163<=30,"DUE <=30 DAYS",IF(H163<=90,"DUE <=90 DAYS","UPCOMING"))) -> OVERDUE | K163: =IF(E163="APPLICATION FILED","Yes","Yes") -> Yes
A164: IP88072 | B164: 202541062777 | C164: HEXITRONICS AUTOMATION LLP | D164: PLEASE PROVIDE | E164: PROVISIONAL FILED | F164: 45839 | G164: =EDATE(DataTable[[#This Row],[Priority Date]],31) -> 45858 | H164: =G164-TODAY() -> -399 | I164: =PendingRQTable[[#This Row],[Days Remaining]]/(365/12) -> -13.117808 | J164: =IF(H164<0,"OVERDUE",IF(H164<=30,"DUE <=30 DAYS",IF(H164<=90,"DUE <=90 DAYS","UPCOMING"))) -> OVERDUE | K164: =IF(E164="PROVISIONAL FILED","Yes","Yes") -> Yes
A165: IP87164 | B165: 202511063152 | C165: ICAR-CENTRAL SHEEP & WOOL RESEARCH INSTITUTE | D165: PLEASE PROVIDE | E165: PROVISIONAL FILED | F165: 45840 | G165: =EDATE(DataTable[[#This Row],[Priority Date]],31) -> 45868 | H165: =G165-TODAY() -> -389 | I165: =PendingRQTable[[#This Row],[Days Remaining]]/(365/12) -> -12.789041 | J165: =IF(H165<0,"OVERDUE",IF(H165<=30,"DUE <=30 DAYS",IF(H165<=90,"DUE <=90 DAYS","UPCOMING"))) -> OVERDUE | K165: =IF(E165="PROVISIONAL FILED","Yes","Yes") -> Yes
A166: IP88460 | B166: 202541064158 | C166: HAMILTON BROOK SMITH REYNOLDS | D166: 4316.1031-001 IN | E166: ABANDONED | F166: 45842 | G166: =EDATE(DataTable[[#This Row],[Priority Date]],31) -> 45879 | H166: =G166-TODAY() -> -378 | I166: =PendingRQTable[[#This Row],[Days Remaining]]/(365/12) -> -12.427397 | J166: =IF(H166<0,"OVERDUE",IF(H166<=30,"DUE <=30 DAYS",IF(H166<=90,"DUE <=90 DAYS","UPCOMING"))) -> OVERDUE | K166: =IF(E166="ABANDONED","No - Case Inactive","Yes") -> No - Case Inactive
A167: IP86963 | B167: 202541064215 | C167: MERCEDES-BENZ INTELLECTUAL PROPERTY GMBH & CO KG | D167: 2025P00793 IN | E167: COMPLETE FILED | F167: 45842 | G167: =EDATE(DataTable[[#This Row],[Priority Date]],31) -> 46793 | H167: =G167-TODAY() -> 536 | I167: =PendingRQTable[[#This Row],[Days Remaining]]/(365/12) -> 17.621918 | J167: =IF(H167<0,"OVERDUE",IF(H167<=30,"DUE <=30 DAYS",IF(H167<=90,"DUE <=90 DAYS","UPCOMING"))) -> UPCOMING | K167: =IF(E167="COMPLETE FILED","Yes","Yes") -> Yes
A168: IP85648 | B168: 202541063903 | C168: AMRITA CENTRE FOR NANOSCIENCES & | D168: ASP-001500INP | E168: PROVISIONAL FILED | F168: 45842 | G168: =EDATE(DataTable[[#This Row],[Priority Date]],31) -> 46793 | H168: =G168-TODAY() -> 536 | I168: =PendingRQTable[[#This Row],[Days Remaining]]/(365/12) -> 17.621918 | J168: =IF(H168<0,"OVERDUE",IF(H168<=30,"DUE <=30 DAYS",IF(H168<=90,"DUE <=90 DAYS","UPCOMING"))) -> UPCOMING | K168: =IF(E168="PROVISIONAL FILED","Yes","Yes") -> Yes
A169: IP87053 | B169: 202541064082 | C169: STRING BIO PRIVATE LIMITED | D169: PLEASE PROVIDE | E169: PROVISIONAL FILED | F169: 45842 | G169: =EDATE(DataTable[[#This Row],[Priority Date]],31) -> 46793 | H169: =G169-TODAY() -> 536 | I169: =PendingRQTable[[#This Row],[Days Remaining]]/(365/12) -> 17.621918 | J169: =IF(H169<0,"OVERDUE",IF(H169<=30,"DUE <=30 DAYS",IF(H169<=90,"DUE <=90 DAYS","UPCOMING"))) -> UPCOMING | K169: =IF(E169="PROVISIONAL FILED","Yes","Yes") -> Yes
A170: IP88375 | B170: 202541064056 | C170: HAYNES AND BOONE LLP | D170: 59103.145PV01 | E170: ABANDONED | F170: 45842 | G170: =EDATE(DataTable[[#This Row],[Priority Date]],31) -> 46793 | H170: =G170-TODAY() -> 536 | I170: =PendingRQTable[[#This Row],[Days Remaining]]/(365/12) -> 17.621918 | J170: =IF(H170<0,"OVERDUE",IF(H170<=30,"DUE <=30 DAYS",IF(H170<=90,"DUE <=90 DAYS","UPCOMING"))) -> UPCOMING | K170: =IF(E170="ABANDONED","No - Case Inactive","Yes") -> No - Case Inactive
A171: IP88439 | B171: 202541063856 | C171: RAKUTEN MOBILE INC | D171: PI25-00358IN01 | E171: PROVISIONAL FILED | F171: 45842 | G171: =EDATE(DataTable[[#This Row],[Priority Date]],31) -> 46428 | H171: =G171-TODAY() -> 171 | I171: =PendingRQTable[[#This Row],[Days Remaining]]/(365/12) -> 5.6219178 | J171: =IF(H171<0,"OVERDUE",IF(H171<=30,"DUE <=30 DAYS",IF(H171<=90,"DUE <=90 DAYS","UPCOMING"))) -> UPCOMING | K171: =IF(E171="PROVISIONAL FILED","Yes","Yes") -> Yes
A172: IP85500 | B172: 202541042715 | C172: MC KUMARI | D172: MS-CPDM-2025-020 | E172: PROVISIONAL FILED | F172: 45843 | G172: =EDATE(DataTable[[#This Row],[Priority Date]],31) -> 45853 | H172: =G172-TODAY() -> -404 | I172: =PendingRQTable[[#This Row],[Days Remaining]]/(365/12) -> -13.282192 | J172: =IF(H172<0,"OVERDUE",IF(H172<=30,"DUE <=30 DAYS",IF(H172<=90,"DUE <=90 DAYS","UPCOMING"))) -> OVERDUE | K172: =IF(E172="PROVISIONAL FILED","Yes","Yes") -> Yes
A173: IP85501 | B173: 202541043951 | C173: MC KUMARI | D173: MS-CPDM-2025-021 | E173: PROVISIONAL FILED | F173: 45844 | G173: =EDATE(DataTable[[#This Row],[Priority Date]],31) -> 46793 | H173: =G173-TODAY() -> 536 | I173: =PendingRQTable[[#This Row],[Days Remaining]]/(365/12) -> 17.621918 | J173: =IF(H173<0,"OVERDUE",IF(H173<=30,"DUE <=30 DAYS",IF(H173<=90,"DUE <=90 DAYS","UPCOMING"))) -> UPCOMING | K173: =IF(E173="PROVISIONAL FILED","Yes","Yes") -> Yes
A174: IP89570 | B174: 202511064704 | C174: DEFENCE RESEARCH & DEVELOPMENT ORG (DRDO) | D174: ERIP/IP/2401039/M/01 | E174: RFE FILED | F174: 45845 | G174: =EDATE(DataTable[[#This Row],[Priority Date]],31) -> 46793 | H174: =G174-TODAY() -> 536 | I174: =PendingRQTable[[#This Row],[Days Remaining]]/(365/12) -> 17.621918 | J174: =IF(H174<0,"OVERDUE",IF(H174<=30,"DUE <=30 DAYS",IF(H174<=90,"DUE <=90 DAYS","UPCOMING"))) -> UPCOMING | K174: =IF(E174="RFE FILED","Yes","Yes") -> Yes
A175: IP88492 | B175: 202541064479 | C175: SUGHRUE MION PLLC | D175: PI25-00371IN02 | E175: COMPLETE FILED | F175: 45845 | G175: =EDATE(DataTable[[#This Row],[Priority Date]],31) -> 45853 | H175: =G175-TODAY() -> -404 | I175: =PendingRQTable[[#This Row],[Days Remaining]]/(365/12) -> -13.282192 | J175: =IF(H175<0,"OVERDUE",IF(H175<=30,"DUE <=30 DAYS",IF(H175<=90,"DUE <=90 DAYS","UPCOMING"))) -> OVERDUE | K175: =IF(E175="COMPLETE FILED","Yes","Yes") -> Yes
A176: IP88489 | B176: 202541065126 | C176: RAKUTEN MOBILE INC | D176: PI25-00368IN02 | E176: PROVISIONAL FILED | F176: 45846 | G176: =EDATE(DataTable[[#This Row],[Priority Date]],31) -> 45867 | H176: =G176-TODAY() -> -390 | I176: =PendingRQTable[[#This Row],[Days Remaining]]/(365/12) -> -12.821918 | J176: =IF(H176<0,"OVERDUE",IF(H176<=30,"DUE <=30 DAYS",IF(H176<=90,"DUE <=90 DAYS","UPCOMING"))) -> OVERDUE | K176: =IF(E176="PROVISIONAL FILED","Yes","Yes") -> Yes
A177: IP88490 | B177: 202541065035 | C177: RAKUTEN MOBILE INC | D177: PI25-00369IN02 | E177: COMPLETE FILED | F177: 45846 | G177: =EDATE(DataTable[[#This Row],[Priority Date]],31) -> 45850 | H177: =G177-TODAY() -> -407 | I177: =PendingRQTable[[#This Row],[Days Remaining]]/(365/12) -> -13.380822 | J177: =IF(H177<0,"OVERDUE",IF(H177<=30,"DUE <=30 DAYS",IF(H177<=90,"DUE <=90 DAYS","UPCOMING"))) -> OVERDUE | K177: =IF(E177="COMPLETE FILED","Yes","Yes") -> Yes
A178: IP88493 | B178: 202541065129 | C178: SUGHRUE MION PLLC | D178: PI25-00366IN02 | E178: COMPLETE FILED | F178: 45846 | G178: =EDATE(DataTable[[#This Row],[Priority Date]],31) -> 45865 | H178: =G178-TODAY() -> -392 | I178: =PendingRQTable[[#This Row],[Days Remaining]]/(365/12) -> -12.887671 | J178: =IF(H178<0,"OVERDUE",IF(H178<=30,"DUE <=30 DAYS",IF(H178<=90,"DUE <=90 DAYS","UPCOMING"))) -> OVERDUE | K178: =IF(E178="COMPLETE FILED","Yes","Yes") -> Yes
A179: IP88488 | B179: 202541064810 | C179: RAKUTEN MOBILE INC | D179: PI25-00367IN02 | E179: COMPLETE FILED | F179: 45846 | G179: =EDATE(DataTable[[#This Row],[Priority Date]],31) -> 45854 | H179: =G179-TODAY() -> -403 | I179: =PendingRQTable[[#This Row],[Days Remaining]]/(365/12) -> -13.249315 | J179: =IF(H179<0,"OVERDUE",IF(H179<=30,"DUE <=30 DAYS",IF(H179<=90,"DUE <=90 DAYS","UPCOMING"))) -> OVERDUE | K179: =IF(E179="COMPLETE FILED","Yes","Yes") -> Yes
A180: IP88496 | B180: 202541064986 | C180: Samsung R&D Institute India-Bangalore Pvt. Ltd. | D180: SRIB-20250703-005 | E180: PROVISIONAL FILED | F180: 45846 | G180: =EDATE(DataTable[[#This Row],[Priority Date]],31) -> 46794 | H180: =G180-TODAY() -> 537 | I180: =PendingRQTable[[#This Row],[Days Remaining]]/(365/12) -> 17.654795 | J180: =IF(H180<0,"OVERDUE",IF(H180<=30,"DUE <=30 DAYS",IF(H180<=90,"DUE <=90 DAYS","UPCOMING"))) -> UPCOMING | K180: =IF(E180="PROVISIONAL FILED","Yes","Yes") -> Yes
A181: IP94644 | B181: 202541065031 | C181: TANLA DIGITAL LABS PRIVATE LIMITED | D181: PLEASE PROVIDE | E181: COMPLETE FILED | F181: 45846 | G181: =EDATE(DataTable[[#This Row],[Priority Date]],31) -> 46794 | H181: =G181-TODAY() -> 537 | I181: =PendingRQTable[[#This Row],[Days Remaining]]/(365/12) -> 17.654795 | J181: =IF(H181<0,"OVERDUE",IF(H181<=30,"DUE <=30 DAYS",IF(H181<=90,"DUE <=90 DAYS","UPCOMING"))) -> UPCOMING | K181: =IF(E181="COMPLETE FILED","Yes","Yes") -> Yes
A182: IP88533 | B182: 202511065658 | C182: Samsung R&D Institute India-Bangalore Pvt. Ltd. | D182: SRIB-20250708-001 | E182: ABANDONED | F182: 45847 | G182: =EDATE(DataTable[[#This Row],[Priority Date]],31) -> 46110 | H182: =G182-TODAY() -> -147 | I182: =PendingRQTable[[#This Row],[Days Remaining]]/(365/12) -> -4.8328767 | J182: =IF(H182<0,"OVERDUE",IF(H182<=30,"DUE <=30 DAYS",IF(H182<=90,"DUE <=90 DAYS","UPCOMING"))) -> OVERDUE | K182: =IF(E182="ABANDONED","No - Case Inactive","Yes") -> No - Case Inactive
A183: IP88526 | B183: 202541065535 | C183: QUALCOMM INCORPORATED | D183: 2404866IN1 | E183: PROVISIONAL FILED | F183: 45847 | G183: =EDATE(DataTable[[#This Row],[Priority Date]],31) -> 45965 | H183: =G183-TODAY() -> -292 | I183: =PendingRQTable[[#This Row],[Days Remaining]]/(365/12) -> -9.6 | J183: =IF(H183<0,"OVERDUE",IF(H183<=30,"DUE <=30 DAYS",IF(H183<=90,"DUE <=90 DAYS","UPCOMING"))) -> OVERDUE | K183: =IF(E183="PROVISIONAL FILED","Yes","Yes") -> Yes
A184: IP88572 | B184: 202511066073 | C184: Samsung R&D Institute India-Bangalore Pvt. Ltd. | D184: SRIB-20250703-003 | E184: PROVISIONAL FILED | F184: 45848 | G184: =EDATE(DataTable[[#This Row],[Priority Date]],31) -> 46794 | H184: =G184-TODAY() -> 537 | I184: =PendingRQTable[[#This Row],[Days Remaining]]/(365/12) -> 17.654795 | J184: =IF(H184<0,"OVERDUE",IF(H184<=30,"DUE <=30 DAYS",IF(H184<=90,"DUE <=90 DAYS","UPCOMING"))) -> UPCOMING | K184: =IF(E184="PROVISIONAL FILED","Yes","Yes") -> Yes
A185: IP88536 | B185: 202541065761 | C185: RAKUTEN MOBILE INC | D185: PI25-00378IN02 | E185: PROVISIONAL FILED | F185: 45848 | G185: =EDATE(DataTable[[#This Row],[Priority Date]],31) -> 46794 | H185: =G185-TODAY() -> 537 | I185: =PendingRQTable[[#This Row],[Days Remaining]]/(365/12) -> 17.654795 | J185: =IF(H185<0,"OVERDUE",IF(H185<=30,"DUE <=30 DAYS",IF(H185<=90,"DUE <=90 DAYS","UPCOMING"))) -> UPCOMING | K185: =IF(E185="PROVISIONAL FILED","Yes","Yes") -> Yes
A186: IP88600 | B186: 202541066317 | C186: QUALCOMM INCORPORATED | D186: 2506124IN1 | E186: PROVISIONAL FILED | F186: 45849 | G186: =EDATE(DataTable[[#This Row],[Priority Date]],31) -> 46022 | H186: =G186-TODAY() -> -235 | I186: =PendingRQTable[[#This Row],[Days Remaining]]/(365/12) -> -7.7260274 | J186: =IF(H186<0,"OVERDUE",IF(H186<=30,"DUE <=30 DAYS",IF(H186<=90,"DUE <=90 DAYS","UPCOMING"))) -> OVERDUE | K186: =IF(E186="PROVISIONAL FILED","Yes","Yes") -> Yes
A187: IP88571 | B187: 202541066562 | C187: Samsung R&D Institute India-Bangalore Pvt. Ltd. | D187: SRIB-20250704-005 | E187: PROVISIONAL FILED | F187: 45849 | G187: =EDATE(DataTable[[#This Row],[Priority Date]],31) -> 46794 | H187: =G187-TODAY() -> 537 | I187: =PendingRQTable[[#This Row],[Days Remaining]]/(365/12) -> 17.654795 | J187: =IF(H187<0,"OVERDUE",IF(H187<=30,"DUE <=30 DAYS",IF(H187<=90,"DUE <=90 DAYS","UPCOMING"))) -> UPCOMING | K187: =IF(E187="PROVISIONAL FILED","Yes","Yes") -> Yes
A188: IP88535 | B188: 202541066281 | C188: SUGHRUE MION PLLC | D188: PI25-00380IN02 | E188: COMPLETE FILED | F188: 45849 | G188: =EDATE(DataTable[[#This Row],[Priority Date]],31) -> 45882 | H188: =G188-TODAY() -> -375 | I188: =PendingRQTable[[#This Row],[Days Remaining]]/(365/12) -> -12.328767 | J188: =IF(H188<0,"OVERDUE",IF(H188<=30,"DUE <=30 DAYS",IF(H188<=90,"DUE <=90 DAYS","UPCOMING"))) -> OVERDUE | K188: =IF(E188="COMPLETE FILED","Yes","Yes") -> Yes
A189: IP88545 | B189: 202511066370 | C189: Samsung R&D Institute India-Bangalore Pvt. Ltd. | D189: SRIB-20250310-004 | E189: PROVISIONAL FILED | F189: 45849 | G189: =EDATE(DataTable[[#This Row],[Priority Date]],31) -> 46794 | H189: =G189-TODAY() -> 537 | I189: =PendingRQTable[[#This Row],[Days Remaining]]/(365/12) -> 17.654795 | J189: =IF(H189<0,"OVERDUE",IF(H189<=30,"DUE <=30 DAYS",IF(H189<=90,"DUE <=90 DAYS","UPCOMING"))) -> UPCOMING | K189: =IF(E189="PROVISIONAL FILED","Yes","Yes") -> Yes
A190: IP88602 | B190: 202541066442 | C190: PERKINS COIE LLP | D190: 119314.8135.IN00 | E190: COMPLETE FILED | F190: 45849 | G190: =EDATE(DataTable[[#This Row],[Priority Date]],31) -> 46794 | H190: =G190-TODAY() -> 537 | I190: =PendingRQTable[[#This Row],[Days Remaining]]/(365/12) -> 17.654795 | J190: =IF(H190<0,"OVERDUE",IF(H190<=30,"DUE <=30 DAYS",IF(H190<=90,"DUE <=90 DAYS","UPCOMING"))) -> UPCOMING | K190: =IF(E190="COMPLETE FILED","Yes","Yes") -> Yes
A191: IP88641 | B191: 202541067380 | C191: RAKUTEN MOBILE INC | D191: PI25-00398IN01 | E191: MERGED | F191: 45853 | G191: =EDATE(DataTable[[#This Row],[Priority Date]],31) -> 45903 | H191: =G191-TODAY() -> -354 | I191: =PendingRQTable[[#This Row],[Days Remaining]]/(365/12) -> -11.638356 | J191: =IF(H191<0,"OVERDUE",IF(H191<=30,"DUE <=30 DAYS",IF(H191<=90,"DUE <=90 DAYS","UPCOMING"))) -> OVERDUE | K191: =IF(E191="MERGED","No - Case Inactive","Yes") -> No - Case Inactive
A192: IP88597 | B192: 202541067637 | C192: Samsung R&D Institute India-Bangalore Pvt. Ltd. | D192: SRIB-20250710-007 | E192: PROVISIONAL FILED | F192: 45853 | G192: =EDATE(DataTable[[#This Row],[Priority Date]],31) -> 46434 | H192: =G192-TODAY() -> 177 | I192: =PendingRQTable[[#This Row],[Days Remaining]]/(365/12) -> 5.8191781 | J192: =IF(H192<0,"OVERDUE",IF(H192<=30,"DUE <=30 DAYS",IF(H192<=90,"DUE <=90 DAYS","UPCOMING"))) -> UPCOMING | K192: =IF(E192="PROVISIONAL FILED","Yes","Yes") -> Yes
A193: IP87132 | B193: 202541067558 | C193: EXSEGEN GENOMICS RESEARCH PRIVATE LIMITED | D193: PLEASE PROVIDE | E193: PROVISIONAL FILED | F193: 45853 | G193: =EDATE(DataTable[[#This Row],[Priority Date]],31) -> 45851 | H193: =G193-TODAY() -> -406 | I193: =PendingRQTable[[#This Row],[Days Remaining]]/(365/12) -> -13.347945 | J193: =IF(H193<0,"OVERDUE",IF(H193<=30,"DUE <=30 DAYS",IF(H193<=90,"DUE <=90 DAYS","UPCOMING"))) -> OVERDUE | K193: =IF(E193="PROVISIONAL FILED","Yes","Yes") -> Yes
A194: IP93407 | B194: 202614051332 | C194: 21ST CENTURY PATENT & LAW FIRM | D194: HZ4037IN/HW | E194: APPLICATION FILED | F194: 46134 | G194: =EDATE(DataTable[[#This Row],[Priority Date]],31) -> 45857 | H194: =G194-TODAY() -> -400 | I194: =PendingRQTable[[#This Row],[Days Remaining]]/(365/12) -> -13.150685 | J194: =IF(H194<0,"OVERDUE",IF(H194<=30,"DUE <=30 DAYS",IF(H194<=90,"DUE <=90 DAYS","UPCOMING"))) -> OVERDUE | K194: =IF(E194="APPLICATION FILED","Yes","Yes") -> Yes
A195: IP88596 | B195: 202541067815 | C195: Samsung R&D Institute India-Bangalore Pvt. Ltd. | D195: SRIB-20250710-005 | E195: PROVISIONAL FILED | F195: 45854 | G195: =EDATE(DataTable[[#This Row],[Priority Date]],31) -> 45850 | H195: =G195-TODAY() -> -407 | I195: =PendingRQTable[[#This Row],[Days Remaining]]/(365/12) -> -13.380822 | J195: =IF(H195<0,"OVERDUE",IF(H195<=30,"DUE <=30 DAYS",IF(H195<=90,"DUE <=90 DAYS","UPCOMING"))) -> OVERDUE | K195: =IF(E195="PROVISIONAL FILED","Yes","Yes") -> Yes
A196: IP88452 | B196: 202511067742 | C196: LEENA ROSE WILSON | D196: PLEASE PROVIDE | E196: PROVISIONAL FILED | F196: 45854 | G196: =EDATE(DataTable[[#This Row],[Priority Date]],31) -> 46794 | H196: =G196-TODAY() -> 537 | I196: =PendingRQTable[[#This Row],[Days Remaining]]/(365/12) -> 17.654795 | J196: =IF(H196<0,"OVERDUE",IF(H196<=30,"DUE <=30 DAYS",IF(H196<=90,"DUE <=90 DAYS","UPCOMING"))) -> UPCOMING | K196: =IF(E196="PROVISIONAL FILED","Yes","Yes") -> Yes
A197: IP88663 | B197: 202541068434 | C197: Samsung R&D Institute India-Bangalore Pvt. Ltd. | D197: SRIB-20250715-002 | E197: PROVISIONAL FILED | F197: 45855 | G197: =EDATE(DataTable[[#This Row],[Priority Date]],31) -> 45860 | H197: =G197-TODAY() -> -397 | I197: =PendingRQTable[[#This Row],[Days Remaining]]/(365/12) -> -13.052055 | J197: =IF(H197<0,"OVERDUE",IF(H197<=30,"DUE <=30 DAYS",IF(H197<=90,"DUE <=90 DAYS","UPCOMING"))) -> OVERDUE | K197: =IF(E197="PROVISIONAL FILED","Yes","Yes") -> Yes
A198: IP86655 | B198: 202541068124 | C198: MERCEDES-BENZ INTELLECTUAL PROPERTY GMBH & CO KG | D198: 2024P03980 IN | E198: COMPLETE FILED | F198: 45855 | G198: =EDATE(DataTable[[#This Row],[Priority Date]],31) -> 45861 | H198: =G198-TODAY() -> -396 | I198: =PendingRQTable[[#This Row],[Days Remaining]]/(365/12) -> -13.019178 | J198: =IF(H198<0,"OVERDUE",IF(H198<=30,"DUE <=30 DAYS",IF(H198<=90,"DUE <=90 DAYS","UPCOMING"))) -> OVERDUE | K198: =IF(E198="COMPLETE FILED","Yes","Yes") -> Yes
A199: IP88670 | B199: 202541068399 | C199: CISCO TECHNOLOGY, INC. | D199: C/P/1066177/IN/PRV/1 | E199: ABANDONED | F199: 45855 | G199: =EDATE(DataTable[[#This Row],[Priority Date]],31) -> 45861 | H199: =G199-TODAY() -> -396 | I199: =PendingRQTable[[#This Row],[Days Remaining]]/(365/12) -> -13.019178 | J199: =IF(H199<0,"OVERDUE",IF(H199<=30,"DUE <=30 DAYS",IF(H199<=90,"DUE <=90 DAYS","UPCOMING"))) -> OVERDUE | K199: =IF(E199="ABANDONED","No - Case Inactive","Yes") -> No - Case Inactive
A200: IP88232 | B200: 202541068817 | C200: MR MURALI NARAYANAN | D200: PLEASE PROVIDE | E200: PROVISIONAL FILED | F200: 45856 | G200: =EDATE(DataTable[[#This Row],[Priority Date]],31) -> 45850 | H200: =G200-TODAY() -> -407 | I200: =PendingRQTable[[#This Row],[Days Remaining]]/(365/12) -> -13.380822 | J200: =IF(H200<0,"OVERDUE",IF(H200<=30,"DUE <=30 DAYS",IF(H200<=90,"DUE <=90 DAYS","UPCOMING"))) -> OVERDUE | K200: =IF(E200="PROVISIONAL FILED","Yes","Yes") -> Yes
A201: IP88724 | B201: 202541068665 | C201: CISCO TECHNOLOGY, INC. | D201: C/P/1066193/IN/PRV/1 | E201: ABANDONED | F201: 45856 | G201: =EDATE(DataTable[[#This Row],[Priority Date]],31) -> 46794 | H201: =G201-TODAY() -> 537 | I201: =PendingRQTable[[#This Row],[Days Remaining]]/(365/12) -> 17.654795 | J201: =IF(H201<0,"OVERDUE",IF(H201<=30,"DUE <=30 DAYS",IF(H201<=90,"DUE <=90 DAYS","UPCOMING"))) -> UPCOMING | K201: =IF(E201="ABANDONED","No - Case Inactive","Yes") -> No - Case Inactive
A202: IP88330 | B202: 202521068686 | C202: INDIAN COUNCIL OF MEDICAL RESEARCH | D202: PM-PF-EM-2025-APR-040 | E202: PROVISIONAL FILED | F202: 45856 | G202: =EDATE(DataTable[[#This Row],[Priority Date]],31) -> 45850 | H202: =G202-TODAY() -> -407 | I202: =PendingRQTable[[#This Row],[Days Remaining]]/(365/12) -> -13.380822 | J202: =IF(H202<0,"OVERDUE",IF(H202<=30,"DUE <=30 DAYS",IF(H202<=90,"DUE <=90 DAYS","UPCOMING"))) -> OVERDUE | K202: =IF(E202="PROVISIONAL FILED","Yes","Yes") -> Yes
A203: IP88716 | B203: 202521068640 | C203: UPL LIMITED | D203: CYPROFLANILIDE + SPINOSAD COMBINATION | E203: PROVISIONAL FILED | F203: 45856 | G203: =EDATE(DataTable[[#This Row],[Priority Date]],31) -> 45858 | H203: =G203-TODAY() -> -399 | I203: =PendingRQTable[[#This Row],[Days Remaining]]/(365/12) -> -13.117808 | J203: =IF(H203<0,"OVERDUE",IF(H203<=30,"DUE <=30 DAYS",IF(H203<=90,"DUE <=90 DAYS","UPCOMING"))) -> OVERDUE | K203: =IF(E203="PROVISIONAL FILED","Yes","Yes") -> Yes
A204: IP88613 | B204: 202541068772 | C204: Samsung R&D Institute India-Bangalore Pvt. Ltd. | D204: SRIB-20250710-004 | E204: PROVISIONAL FILED | F204: 45856 | G204: =EDATE(DataTable[[#This Row],[Priority Date]],31) -> 46466 | H204: =G204-TODAY() -> 209 | I204: =PendingRQTable[[#This Row],[Days Remaining]]/(365/12) -> 6.8712329 | J204: =IF(H204<0,"OVERDUE",IF(H204<=30,"DUE <=30 DAYS",IF(H204<=90,"DUE <=90 DAYS","UPCOMING"))) -> UPCOMING | K204: =IF(E204="PROVISIONAL FILED","Yes","Yes") -> Yes
A205: IP88785 | B205: 202541069525 | C205: Samsung R&D Institute India-Bangalore Pvt. Ltd. | D205: SRIB-20250718-001 | E205: PROVISIONAL FILED | F205: 45859 | G205: =EDATE(DataTable[[#This Row],[Priority Date]],31) -> 46467 | H205: =G205-TODAY() -> 210 | I205: =PendingRQTable[[#This Row],[Days Remaining]]/(365/12) -> 6.9041096 | J205: =IF(H205<0,"OVERDUE",IF(H205<=30,"DUE <=30 DAYS",IF(H205<=90,"DUE <=90 DAYS","UPCOMING"))) -> UPCOMING | K205: =IF(E205="PROVISIONAL FILED","Yes","Yes") -> Yes
A206: IP94917 | B206: 202541069375 | C206: LMW LIMITED | D206: BR27 | E206: PROVISIONAL FILED | F206: 45859 | G206: =EDATE(DataTable[[#This Row],[Priority Date]],31) -> 45854 | H206: =G206-TODAY() -> -403 | I206: =PendingRQTable[[#This Row],[Days Remaining]]/(365/12) -> -13.249315 | J206: =IF(H206<0,"OVERDUE",IF(H206<=30,"DUE <=30 DAYS",IF(H206<=90,"DUE <=90 DAYS","UPCOMING"))) -> OVERDUE | K206: =IF(E206="PROVISIONAL FILED","Yes","Yes") -> Yes
A207: IP85587 | B207: 202541038273 | C207: TITAN COMPANY LIMITED | D207: IDF1- 2354-2025 | E207: PROVISIONAL FILED | F207: 45859 | G207: =EDATE(DataTable[[#This Row],[Priority Date]],31) -> 45857 | H207: =G207-TODAY() -> -400 | I207: =PendingRQTable[[#This Row],[Days Remaining]]/(365/12) -> -13.150685 | J207: =IF(H207<0,"OVERDUE",IF(H207<=30,"DUE <=30 DAYS",IF(H207<=90,"DUE <=90 DAYS","UPCOMING"))) -> OVERDUE | K207: =IF(E207="PROVISIONAL FILED","Yes","Yes") -> Yes
A208: IP88821 | B208: 202541070047 | C208: QUALCOMM INCORPORATED | D208: 2505943IN1 | E208: PROVISIONAL FILED | F208: 45861 | G208: =EDATE(DataTable[[#This Row],[Priority Date]],31) -> 45906 | H208: =G208-TODAY() -> -351 | I208: =PendingRQTable[[#This Row],[Days Remaining]]/(365/12) -> -11.539726 | J208: =IF(H208<0,"OVERDUE",IF(H208<=30,"DUE <=30 DAYS",IF(H208<=90,"DUE <=90 DAYS","UPCOMING"))) -> OVERDUE | K208: =IF(E208="PROVISIONAL FILED","Yes","Yes") -> Yes
A209: IP88806 | B209: 202541069976 | C209: RAKUTEN MOBILE INC | D209: PI25-00407IN01 | E209: MERGED | F209: 45861 | G209: =EDATE(DataTable[[#This Row],[Priority Date]],31) -> 46072 | H209: =G209-TODAY() -> -185 | I209: =PendingRQTable[[#This Row],[Days Remaining]]/(365/12) -> -6.0821918 | J209: =IF(H209<0,"OVERDUE",IF(H209<=30,"DUE <=30 DAYS",IF(H209<=90,"DUE <=90 DAYS","UPCOMING"))) -> OVERDUE | K209: =IF(E209="MERGED","No - Case Inactive","Yes") -> No - Case Inactive
A210: IP88871 | B210: 202521070277 | C210: UPL LIMITED | D210: CYPROFLANILIDE 250 SC | E210: PROVISIONAL FILED | F210: 45861 | G210: =EDATE(DataTable[[#This Row],[Priority Date]],31) -> 45858 | H210: =G210-TODAY() -> -399 | I210: =PendingRQTable[[#This Row],[Days Remaining]]/(365/12) -> -13.117808 | J210: =IF(H210<0,"OVERDUE",IF(H210<=30,"DUE <=30 DAYS",IF(H210<=90,"DUE <=90 DAYS","UPCOMING"))) -> OVERDUE | K210: =IF(E210="PROVISIONAL FILED","Yes","Yes") -> Yes
A211: IP88874 | B211: 202541070310 | C211: NETAPP, INC. | D211: P-013103-IN | E211: ABANDONED | F211: 45861 | G211: =EDATE(DataTable[[#This Row],[Priority Date]],31) -> 46797 | H211: =G211-TODAY() -> 540 | I211: =PendingRQTable[[#This Row],[Days Remaining]]/(365/12) -> 17.753425 | J211: =IF(H211<0,"OVERDUE",IF(H211<=30,"DUE <=30 DAYS",IF(H211<=90,"DUE <=90 DAYS","UPCOMING"))) -> UPCOMING | K211: =IF(E211="ABANDONED","No - Case Inactive","Yes") -> No - Case Inactive
A212: IP88395 | B212: 202521070092 | C212: TATA PLAY LIMITED | D212: PLEASE PROVIDE | E212: PROVISIONAL FILED | F212: 45861 | G212: =EDATE(DataTable[[#This Row],[Priority Date]],31) -> 45854 | H212: =G212-TODAY() -> -403 | I212: =PendingRQTable[[#This Row],[Days Remaining]]/(365/12) -> -13.249315 | J212: =IF(H212<0,"OVERDUE",IF(H212<=30,"DUE <=30 DAYS",IF(H212<=90,"DUE <=90 DAYS","UPCOMING"))) -> OVERDUE | K212: =IF(E212="PROVISIONAL FILED","Yes","Yes") -> Yes
A213: IP88793 | B213: 202511070038 | C213: Samsung R&D Institute India-Bangalore Pvt. Ltd. | D213: SRIB-20250721-003 | E213: MERGED | F213: 45861 | G213: =EDATE(DataTable[[#This Row],[Priority Date]],31) -> 45859 | H213: =G213-TODAY() -> -398 | I213: =PendingRQTable[[#This Row],[Days Remaining]]/(365/12) -> -13.084932 | J213: =IF(H213<0,"OVERDUE",IF(H213<=30,"DUE <=30 DAYS",IF(H213<=90,"DUE <=90 DAYS","UPCOMING"))) -> OVERDUE | K213: =IF(E213="MERGED","No - Case Inactive","Yes") -> No - Case Inactive
A214: IP88828 | B214: 202541070477 | C214: FOLEY & LARDNER LLP | D214: 106389-9561 | E214: COMPLETE FILED | F214: 45862 | G214: =EDATE(DataTable[[#This Row],[Priority Date]],31) -> 45857 | H214: =G214-TODAY() -> -400 | I214: =PendingRQTable[[#This Row],[Days Remaining]]/(365/12) -> -13.150685 | J214: =IF(H214<0,"OVERDUE",IF(H214<=30,"DUE <=30 DAYS",IF(H214<=90,"DUE <=90 DAYS","UPCOMING"))) -> OVERDUE | K214: =IF(E214="COMPLETE FILED","Yes","Yes") -> Yes
A215: IP88880 | B215: 202541070578 | C215: QUALCOMM INCORPORATED | D215: 2505307IN1 | E215: PROVISIONAL FILED | F215: 45862 | G215: =EDATE(DataTable[[#This Row],[Priority Date]],31) -> 45928 | H215: =G215-TODAY() -> -329 | I215: =PendingRQTable[[#This Row],[Days Remaining]]/(365/12) -> -10.816438 | J215: =IF(H215<0,"OVERDUE",IF(H215<=30,"DUE <=30 DAYS",IF(H215<=90,"DUE <=90 DAYS","UPCOMING"))) -> OVERDUE | K215: =IF(E215="PROVISIONAL FILED","Yes","Yes") -> Yes
A216: IP87183 | B216: 202541070503 | C216: Centre for Industrial Consultancy | D216: SR NO.: S 2025-26/2228 & THE IDF NO. 3363. | E216: PROVISIONAL FILED | F216: 45862 | G216: =EDATE(DataTable[[#This Row],[Priority Date]],31) -> 46797 | H216: =G216-TODAY() -> 540 | I216: =PendingRQTable[[#This Row],[Days Remaining]]/(365/12) -> 17.753425 | J216: =IF(H216<0,"OVERDUE",IF(H216<=30,"DUE <=30 DAYS",IF(H216<=90,"DUE <=90 DAYS","UPCOMING"))) -> UPCOMING | K216: =IF(E216="PROVISIONAL FILED","Yes","Yes") -> Yes
A217: IP85742 | B217: 202541070855 | C217: INDIAN INSTITUTE OF SCIENCE | D217: MS-MAT-2025-027 | E217: PROVISIONAL FILED | F217: 45863 | G217: =EDATE(DataTable[[#This Row],[Priority Date]],31) -> 46133 | H217: =G217-TODAY() -> -124 | I217: =PendingRQTable[[#This Row],[Days Remaining]]/(365/12) -> -4.0767123 | J217: =IF(H217<0,"OVERDUE",IF(H217<=30,"DUE <=30 DAYS",IF(H217<=90,"DUE <=90 DAYS","UPCOMING"))) -> OVERDUE | K217: =IF(E217="PROVISIONAL FILED","Yes","Yes") -> Yes
A218: IP86053 | B218: 202541071101 | C218: STRING BIO PRIVATE LIMITED | D218: PLEASE PROVIDE | E218: PROVISIONAL FILED | F218: 45863 | G218: =EDATE(DataTable[[#This Row],[Priority Date]],31) -> 46797 | H218: =G218-TODAY() -> 540 | I218: =PendingRQTable[[#This Row],[Days Remaining]]/(365/12) -> 17.753425 | J218: =IF(H218<0,"OVERDUE",IF(H218<=30,"DUE <=30 DAYS",IF(H218<=90,"DUE <=90 DAYS","UPCOMING"))) -> UPCOMING | K218: =IF(E218="PROVISIONAL FILED","Yes","Yes") -> Yes
A219: IP88896 | B219: 202541071124 | C219: Samsung R&D Institute India-Bangalore Pvt. Ltd. | D219: SRIB-20250723-003 | E219: PROVISIONAL FILED | F219: 45863 | G219: =EDATE(DataTable[[#This Row],[Priority Date]],31) -> 45859 | H219: =G219-TODAY() -> -398 | I219: =PendingRQTable[[#This Row],[Days Remaining]]/(365/12) -> -13.084932 | J219: =IF(H219<0,"OVERDUE",IF(H219<=30,"DUE <=30 DAYS",IF(H219<=90,"DUE <=90 DAYS","UPCOMING"))) -> OVERDUE | K219: =IF(E219="PROVISIONAL FILED","Yes","Yes") -> Yes
A220: IP84263 | B220: 202511040481 | C220: POLYPLEX CORPORATION LTD | D220: PLEASE PROVIDE | E220: PROVISIONAL FILED | F220: 45864 | G220: =EDATE(DataTable[[#This Row],[Priority Date]],31) -> 45975 | H220: =G220-TODAY() -> -282 | I220: =PendingRQTable[[#This Row],[Days Remaining]]/(365/12) -> -9.2712329 | J220: =IF(H220<0,"OVERDUE",IF(H220<=30,"DUE <=30 DAYS",IF(H220<=90,"DUE <=90 DAYS","UPCOMING"))) -> OVERDUE | K220: =IF(E220="PROVISIONAL FILED","Yes","Yes") -> Yes
A221: IP86054 | B221: 202541071428 | C221: STRING BIO PRIVATE LIMITED | D221: PLEASE PROVIDE | E221: PROVISIONAL FILED | F221: 45866 | G221: =EDATE(DataTable[[#This Row],[Priority Date]],31) -> 45859 | H221: =G221-TODAY() -> -398 | I221: =PendingRQTable[[#This Row],[Days Remaining]]/(365/12) -> -13.084932 | J221: =IF(H221<0,"OVERDUE",IF(H221<=30,"DUE <=30 DAYS",IF(H221<=90,"DUE <=90 DAYS","UPCOMING"))) -> OVERDUE | K221: =IF(E221="PROVISIONAL FILED","Yes","Yes") -> Yes
A222: IP95213 | B222: 202541071693 | C222: Samsung R&D Institute India-Bangalore Pvt. Ltd. | D222: SRIB-20250710-006 | E222: PROVISIONAL FILED | F222: 45866 | G222: =EDATE(DataTable[[#This Row],[Priority Date]],31) -> 46798 | H222: =G222-TODAY() -> 541 | I222: =PendingRQTable[[#This Row],[Days Remaining]]/(365/12) -> 17.786301 | J222: =IF(H222<0,"OVERDUE",IF(H222<=30,"DUE <=30 DAYS",IF(H222<=90,"DUE <=90 DAYS","UPCOMING"))) -> UPCOMING | K222: =IF(E222="PROVISIONAL FILED","Yes","Yes") -> Yes
A223: IP88854 | B223: 202541071448 | C223: Samsung R&D Institute India-Bangalore Pvt. Ltd. | D223: SRIB-20250722-008 | E223: PROVISIONAL FILED | F223: 45866 | G223: =EDATE(DataTable[[#This Row],[Priority Date]],31) -> 45860 | H223: =G223-TODAY() -> -397 | I223: =PendingRQTable[[#This Row],[Days Remaining]]/(365/12) -> -13.052055 | J223: =IF(H223<0,"OVERDUE",IF(H223<=30,"DUE <=30 DAYS",IF(H223<=90,"DUE <=90 DAYS","UPCOMING"))) -> OVERDUE | K223: =IF(E223="PROVISIONAL FILED","Yes","Yes") -> Yes
A224: IP88741 | B224: 202521071543 | C224: TATA MOTORS LIMITED | D224: 13103 | E224: PROVISIONAL FILED | F224: 45866 | G224: =EDATE(DataTable[[#This Row],[Priority Date]],31) -> 46798 | H224: =G224-TODAY() -> 541 | I224: =PendingRQTable[[#This Row],[Days Remaining]]/(365/12) -> 17.786301 | J224: =IF(H224<0,"OVERDUE",IF(H224<=30,"DUE <=30 DAYS",IF(H224<=90,"DUE <=90 DAYS","UPCOMING"))) -> UPCOMING | K224: =IF(E224="PROVISIONAL FILED","Yes","Yes") -> Yes
A225: IP88453 | B225: 202511071443 | C225: WAX GMBH | D225: PLEASE PROVIDE | E225: PROVISIONAL FILED | F225: 45866 | G225: =EDATE(DataTable[[#This Row],[Priority Date]],31) -> 46798 | H225: =G225-TODAY() -> 541 | I225: =PendingRQTable[[#This Row],[Days Remaining]]/(365/12) -> 17.786301 | J225: =IF(H225<0,"OVERDUE",IF(H225<=30,"DUE <=30 DAYS",IF(H225<=90,"DUE <=90 DAYS","UPCOMING"))) -> UPCOMING | K225: =IF(E225="PROVISIONAL FILED","Yes","Yes") -> Yes
A226: IP85774 | B226: 202541071630 | C226: STRING BIO PRIVATE LIMITED | D226: PLEASE PROVIDE | E226: PROVISIONAL FILED | F226: 45866 | G226: =EDATE(DataTable[[#This Row],[Priority Date]],31) -> 46798 | H226: =G226-TODAY() -> 541 | I226: =PendingRQTable[[#This Row],[Days Remaining]]/(365/12) -> 17.786301 | J226: =IF(H226<0,"OVERDUE",IF(H226<=30,"DUE <=30 DAYS",IF(H226<=90,"DUE <=90 DAYS","UPCOMING"))) -> UPCOMING | K226: =IF(E226="PROVISIONAL FILED","Yes","Yes") -> Yes
... A231: IP87930 | B231: 202511072173 | C231: MINDA CORPORATION LIMITED | D231: PLEASE PROVIDE | E231: PROVISIONAL FILED | F231: 45867 | G231: =EDATE(DataTable[[#This Row],[Priority Date]],31) -> 46798 | H231: =G231-TODAY() -> 541 | I231: =PendingRQTable[[#This Row],[Days Remaining]]/(365/12) -> 17.786301 | J231: =IF(H231<0,"OVERDUE",IF(H231<=30,"DUE <=30 DAYS",IF(H231<=90,"DUE <=90 DAYS","UPCOMING"))) -> UPCOMING | K231: =IF(E231="PROVISIONAL FILED","Yes","Yes") -> Yes
A232: IP88088 | B232: 202541072192 | C232: RAKUTEN MOBILE INC | D232: PI25-00264IN01 | E232: COMPLETE FILED | F232: 45867 | G232: =EDATE(DataTable[[#This Row],[Priority Date]],31) -> 45947 | H232: =G232-TODAY() -> -310 | I232: =PendingRQTable[[#This Row],[Days Remaining]]/(365/12) -> -10.191781 | J232: =IF(H232<0,"OVERDUE",IF(H232<=30,"DUE <=30 DAYS",IF(H232<=90,"DUE <=90 DAYS","UPCOMING"))) -> OVERDUE | K232: =IF(E232="COMPLETE FILED","Yes","Yes") -> Yes
A233: IP88815 | B233: 202511071957 | C233: Samsung R&D Institute India-Bangalore Pvt. Ltd. | D233: SRIB-20250722-009 | E233: PROVISIONAL FILED | F233: 45867 | G233: =EDATE(DataTable[[#This Row],[Priority Date]],31) -> 46434 | H233: =G233-TODAY() -> 177 | I233: =PendingRQTable[[#This Row],[Days Remaining]]/(365/12) -> 5.8191781 | J233: =IF(H233<0,"OVERDUE",IF(H233<=30,"DUE <=30 DAYS",IF(H233<=90,"DUE <=90 DAYS","UPCOMING"))) -> UPCOMING | K233: =IF(E233="PROVISIONAL FILED","Yes","Yes") -> Yes
A234: IP88999 | B234: 202541072578 | C234: CISCO TECHNOLOGY, INC. | D234: C/P/1066103/IN/PRV/1 | E234: PROVISIONAL FILED | F234: 45868 | G234: =EDATE(DataTable[[#This Row],[Priority Date]],31) -> 45858 | H234: =G234-TODAY() -> -399 | I234: =PendingRQTable[[#This Row],[Days Remaining]]/(365/12) -> -13.117808 | J234: =IF(H234<0,"OVERDUE",IF(H234<=30,"DUE <=30 DAYS",IF(H234<=90,"DUE <=90 DAYS","UPCOMING"))) -> OVERDUE | K234: =IF(E234="PROVISIONAL FILED","Yes","Yes") -> Yes
A235: IP88954 | B235: 202511072067 | C235: Samsung R&D Institute India-Bangalore Pvt. Ltd. | D235: SRIB-20250728-002 | E235: MERGED | F235: 45867 | G235: =EDATE(DataTable[[#This Row],[Priority Date]],31) -> 46798 | H235: =G235-TODAY() -> 541 | I235: =PendingRQTable[[#This Row],[Days Remaining]]/(365/12) -> 17.786301 | J235: =IF(H235<0,"OVERDUE",IF(H235<=30,"DUE <=30 DAYS",IF(H235<=90,"DUE <=90 DAYS","UPCOMING"))) -> UPCOMING | K235: =IF(E235="MERGED","No - Case Inactive","Yes") -> No - Case Inactive
A236: IP88998 | B236: 202541072516 | C236: QUALCOMM INCORPORATED | D236: 2507129IN1 | E236: PROVISIONAL FILED | F236: 45868 | G236: =EDATE(DataTable[[#This Row],[Priority Date]],31) -> 45857 | H236: =G236-TODAY() -> -400 | I236: =PendingRQTable[[#This Row],[Days Remaining]]/(365/12) -> -13.150685 | J236: =IF(H236<0,"OVERDUE",IF(H236<=30,"DUE <=30 DAYS",IF(H236<=90,"DUE <=90 DAYS","UPCOMING"))) -> OVERDUE | K236: =IF(E236="PROVISIONAL FILED","Yes","Yes") -> Yes
A237: IP87788 | B237: 202541072006 | C237: RAKUTEN MOBILE INC | D237: PI25-00197IN01 | E237: COMPLETE FILED | F237: 45867 | G237: =EDATE(DataTable[[#This Row],[Priority Date]],31) -> 45864 | H237: =G237-TODAY() -> -393 | I237: =PendingRQTable[[#This Row],[Days Remaining]]/(365/12) -> -12.920548 | J237: =IF(H237<0,"OVERDUE",IF(H237<=30,"DUE <=30 DAYS",IF(H237<=90,"DUE <=90 DAYS","UPCOMING"))) -> OVERDUE | K237: =IF(E237="COMPLETE FILED","Yes","Yes") -> Yes
A238: IP87406 | B238: 202521073463 | C238: COMFORT GRID TECHNOLOGIES PRIVATE LIMITED | D238: PLEASE PROVIDE | E238: COMPLETE FILED | F238: 45870 | G238: =EDATE(DataTable[[#This Row],[Priority Date]],31) -> 45860 | H238: =G238-TODAY() -> -397 | I238: =PendingRQTable[[#This Row],[Days Remaining]]/(365/12) -> -13.052055 | J238: =IF(H238<0,"OVERDUE",IF(H238<=30,"DUE <=30 DAYS",IF(H238<=90,"DUE <=90 DAYS","UPCOMING"))) -> OVERDUE | K238: =IF(E238="COMPLETE FILED","Yes","Yes") -> Yes
...

Sheet Status Overview
A1: Status | B1: Case Count | C1: % of Total
A2: RFE FILED | B2: =COUNTIF(Data!$R$2:$R$6232,A2) -> 4607 | C2: =B2/6052 -> 0.76123596
A3: PROVISIONAL FILED | B3: =COUNTIF(Data!$R$2:$R$6232,A3) -> 805 | C3: =B3/6052 -> 0.13301388
A4: COMPLETE FILED | B4: =COUNTIF(Data!$R$2:$R$6232,A4) -> 245 | C4: =B4/6052 -> 0.040482485
A5: APPLICATION FILED | B5: =COUNTIF(Data!$R$2:$R$6232,A5) -> 171 | C5: =B5/6052 -> 0.028255122
A6: UNDER EXAMINATION | B6: =COUNTIF(Data!$R$2:$R$6232,A6) -> 74 | C6: =B6/6052 -> 0.012227363
A7: ABANDONED | B7: =COUNTIF(Data!$R$2:$R$6232,A7) -> 63 | C7: =B7/6052 -> 0.010409782
A8: RE-FILED | B8: =COUNTIF(Data!$R$2:$R$6232,A8) -> 23 | C8: =B8/6052 -> 0.0038003966
A9: CLOSED | B9: =COUNTIF(Data!$R$2:$R$6232,A9) -> 17 | C9: =B9/6052 -> 0.0028089888
A10: GRANTED | B10: =COUNTIF(Data!$R$2:$R$6232,A10) -> 13 | C10: =B10/6052 -> 0.0021480502
A11: DO NOT INCUR | B11: =COUNTIF(Data!$R$2:$R$6232,A11) -> 9 | C11: =B11/6052 -> 0.0014871117
A12: WITHDRAWAL FILED(REFUND) | B12: =COUNTIF(Data!$R$2:$R$6232,A12) -> 8 | C12: =B12/6052 -> 0.0013218771
A13: HEARING | B13: =COUNTIF(Data!$R$2:$R$6232,A13) -> 6 | C13: =B13/6052 -> 0.0009914078
... A18: DRAFTING | B18: =COUNTIF(Data!$R$2:$R$6232,A18) -> 1 | C18: =B18/6052 -> 0.00016523463
A20: TOTAL | B20: =SUM(B2:B18) -> 6052

Sheet Data
A1: Sr. No. | B1: File No | C1: Application No | D1: Client Name | E1: Client Ref | F1: Client Country | G1: Applicant | H1: Title | I1: Provisional/Complete | J1: Branch | K1: Case Recv. On | L1: Priority Date | M1: Filing Date | N1: RQ Due | O1: RQ Filed | P1: Attorney | Q1: Paralegal | R1: Status
A2: 1 | B2: IP88038 | C2: 202517062668 | D2: CROSS-BORDER PATENT FIRM | E2: 684500IN01OMNA | F2: Japan | G2: MITSUBISHI ELECTRIC CORPORATION | H2: STATE TRANSITION MANAGEMENT APPARATUS AND STATE TRANSITION MANAGEMENT METHOD PCT/JP2023/005999 | J2: GURGAON | K2: 45821 | L2: 45839 | M2: 45839 | O2: 45839 | P2: Sumukh A | Q2: Ravi Mishra | R2: RFE FILED
A3: 2 | B3: IP85070 | C3: 202511062810 | D3: The Director ICAR NIVEDI | E3: PLEASE PROVIDE | F3: India | G3: INDIAN COUNCIL OF AGRICULTURAL RESEARCH (ICAR) | H3: RECOMBINANT MUTANT EPSILON (rETX) FUSION PROTEIN AND THE METHOD OF PREPARATION THEREOF | I3: Complete Filed | J3: GURGAON | K3: 45678 | L3: 45839 | M3: 45839 | O3: 45846 | P3: Samriti Sanjgotra | Q3: Nitika Anand | R3: RFE FILED
A4: 3 | B4: IP88153 | C4: 202544062608 | D4: GRUNECKER | E4: PA148458IN-TG433903JFE | F4: Germany | G4: KRONES AG | H4: CONTAINER TREATMENT MACHINE FOR TREATING CONTAINERS | J4: GURGAON | K4: 45827 | L4: 45485 | M4: 45839 | O4: 45839 | P4: Sandesh Sastry | Q4: Gurleen Kaur | R4: RFE FILED
A5: 4 | B5: IP87829 | C5: 202517062664 | D5: YOU ME PATENT & LAW FIRM | E5: OPP20243406IN | F5: Korea | G5: LG ENERGY SOLUTION, LTD. | H5: APPARATUS AND METHOD OF ESTIMATING THE BATTERY INTERNAL RESISTANCE PCT/KR2024/008470 | J5: GURGAON | K5: 45812 | L5: 45278 | M5: 45839 | O5: 45839 | P5: Sonali Mewar | Q5: Arun Kumar | R5: RFE FILED
A6: 5 | B6: IP86294 | C6: 202517062728 | D6: YOU ME PATENT & LAW FIRM | E6: OPP20250928IN | F6: Korea | G6: POSCO CO., LTD | H6: ADHESIVE COATING COMPOSITION FOR ELECTRICAL STEEL SHEET, ELECTRICAL STEEL SHEET LAMINATE, AND METHOD FOR MANUFACTURING SAME PCT/KR2023/017729 | J6: GURGAON | K6: 45729 | L6: 44916 | M6: 45839 | O6: 45839 | P6: Yameeni Sarothia | Q6: Arub Mistree | R6: RFE FILED
A7: 6 | B7: IP85682 | C7: 202544062757 | D7: KASAN IP & LAW FIRM | E7: SMP230511IN | F7: Korea | G7: SAMSUNG DISPLAY CO., LTD. | H7: DISPLAY DEVICE AND OPTICAL DEVICE INCLUDING THE SAME | J7: GURGAON | K7: 45708 | L7: 45474 | M7: 45839 | N7: 46419 | P7: Mohamed Ghouse | Q7: Ravi Prakashan PK | R7: APPLICATION FILED
A8: 7 | B8: IP86368 | C8: 202541062582 | D8: INDIAN INSTITUTE OF SCIENCE | E8: CS-OC-2025-043 | F8: India | G8: INDIAN INSTITUTE OF SCIENCE | H8: IONIZABLE LIPID PROCESS OF PREPARING SAME AND APPLICATIONS THEREOF | I8: Complete Filed | J8: GURGAON | K8: 45733 | L8: 45839 | M8: 45839 | O8: 45839 | P8: Indrani Adhikari | Q8: Sunil Gaur | R8: RFE FILED
A9: 8 | B9: IP86936 | C9: 202541062563 | D9: INDIAN INSTITUTE OF SCIENCE | E9: CS-OC-2025-064 | F9: India | G9: INDIAN INSTITUTE OF SCIENCE | H9: PROCESS FOR PREPARATION OF IONIZABLE LIPIDS | I9: Complete Filed | J9: GURGAON | K9: 45763 | L9: 45839 | M9: 45839 | O9: 45839 | P9: Indrani Adhikari | Q9: Sunil Gaur | R9: GRANTED
A10: 9 | B10: IP88253 | C10: 202547062617 | D10: QUALCOMM INCORPORATED | E10: 2207346IN | F10: United States Of America | G10: QUALCOMM INCORPORATED | H10: USER EQUIPMENT (UE) FULL-DUPLEX OPERATION PCT/US2024/012185 | J10: GURGAON | K10: 45833 | L10: 44965 | M10: 45839 | O10: 45839 | P10: Abhimanyu Singh | Q10: Anand Yenurkar | R10: RFE FILED
A11: 10 | B11: IP88255 | C11: 202547062788 | D11: QUALCOMM INCORPORATED | E11: 2208615IN | F11: United States Of America | G11: QUALCOMM INCORPORATED | H11: POSITION SENSING BASED ON RECONFIGURABLE INTELLIGENT SURFACE (RIS) REFLECTION SCHEDULE PCT/CN2023/074750 | J11: GURGAON | K11: 45833 | L11: 45839 | M11: 45839 | O11: 45839 | P11: Harshitha R | Q11: Chaitra K G | R11: RFE FILED
A12: 11 | B12: IP88281 | C12: 202547062774 | D12: QUALCOMM INCORPORATED | E12: 2301877IN | F12: United States Of America | G12: QUALCOMM INCORPORATED | H12: RESOURCE BLOCK GROUP SIZES PCT/US2024/014507 | J12: GURGAON | K12: 45833 | L12: 44967 | M12: 45839 | O12: 45839 | P12: Kshama Gaitonde | Q12: Mani V S | R12: RFE FILED
A13: 12 | B13: IP87727 | C13: 202517062809 | D13: LATHROP GPM LLP | E13: 766130: KNT-001IN | F13: United States Of America | G13: KINASET THERAPEUTICS, INC. | H13: FORMULATION OF A PAN-JAK INHIBITOR PCT/US2023/082047 | J13: GURGAON | K13: 45807 | L13: 44897 | M13: 45839 | O13: 45839 | P13: Anamika Thakur | Q13: Ranjana Verma | R13: RFE FILED
A14: 13 | B14: IP87956 | C14: 202517062769 | D14: SAKAI INTERNATIONAL PATENT OFFICE | E14: PMAA-250092-IN | F14: Japan | G14: MITSUBISHI ELECTRIC CORPORATION | H14: SYNCHRONOUS RELUCTANCE MOTOR ABNORMALITY DETECTION DEVICE AND ABNORMALITY DETECTION METHOD PCT/JP2023/001968 | J14: GURGAON | K14: 45818 | L14: 45839 | M14: 45839 | O14: 45839 | P14: Sanjit Kumar | Q14: Anand Yenurkar | R14: RFE FILED
A15: 14 | B15: IP86672 | C15: 202547062727 | D15: JUNHE LAW OFFICES | E15: 087718-8004IN01 | F15: China | G15: SHANGHAI ARGO BIOPHARMACEUTICAL CO., LTD | H15: BICYCLIC ABASIC NUCLEIC ACID ANALOGS AND OLIGOMERIC COMPOUNDS PREPARED THEREFROM PCT/CN2023/135759 | J15: GURGAON | K15: 45747 | L15: 44897 | M15: 45839 | O15: 45839 | P15: Sneha Menon | Q15: Renuka R | R15: RFE FILED
A16: 15 | B16: IP87069 | C16: 202517062627 | D16: KADOR & PARTNER | E16: K 76 272/13DO | F16: Germany | G16: BOREALIS AG | H16: PROCESS FOR PRODUCING A POLYPROPYLENE COPOLYMER PCT/EP2023/086302 | J16: GURGAON | K16: 45770 | L16: 44918 | M16: 45839 | O16: 45845 | P16: Indrani Adhikari | Q16: Sunil Gaur | R16: RFE FILED
A17: 16 | B17: IP87641 | C17: 202517062618 | D17: K&L GATES LLP | E17: 1959952.00050 | F17: United States Of America | G17: ASPERA BIOMEDICINES, INC. | H17: CHEMOENZYMATIC SYNTHESIS OF POLYKETIDES PCT/US2023/082140 | J17: GURGAON | K17: 45803 | L17: 44896 | M17: 45839 | O17: 45839 | P17: Juhi Rajiv Sakrikar | Q17: Gaurav Gupta | R17: RFE FILED
A18: 17 | B18: IP87835 | C18: 202517062731 | D18: PHIL & ONZI | E18: OVP2425164IN | F18: Korea | G18: LG ENERGY SOLUTION, LTD. | H18: WELDING HEAT-SHIELDING MEMBER, ELECTRODE ASSEMBLY DAMAGE PREVENTION STRUCTURE USING SAME, AND BATTERY CELL USING SAME PCT/KR2024/007517 | J18: GURGAON | K18: 45812 | L18: 45104 | M18: 45839 | O18: 45839 | P18: Ankur Saxena | Q18: Shalu Saxena | R18: RFE FILED
A19: 18 | B19: IP88346 | C19: 202517062706 | D19: IBM CORPORATION | E19: P202202274IN01 | F19: United States Of America | G19: INTERNATIONAL BUSINESS MACHINES CORPORATION | H19: PROXIMITY HEATER TO LOWER RRAM FORMING VOLTAGE PCT/EP2023/083112 | J19: GURGAON | K19: 45835 | L19: 44897 | M19: 45839 | O19: 45839 | P19: Riti Sethi | Q19: Manas Maity | R19: RFE FILED
A20: 19 | B20: IP88349 | C20: 202517062987 | D20: IBM CORPORATION | E20: P202201514IN01 | F20: United States Of America | G20: INTERNATIONAL BUSINESS MACHINES CORPORATION | H20: PHASE-CHANGE MEMORY CELL WITH MIXED-MATERIAL SWITCHABLE REGION PCT/CN2023/132548 | J20: GURGAON | K20: 45835 | L20: 44903 | M20: 45839 | O20: 45839 | P20: Sanjit Kumar | Q20: Anand Yenurkar | R20: RFE FILED
A21: 20 | B21: IP88209 | C21: 202547062688 | D21: IPG PHOTONICS CORPORATION | E21: P22381/IN | F21: United States Of America | G21: IPG PHOTONICS CORPORATION | H21: PROTECTIVE MULTIWINDOW CARTRIDGE ASSEMBLY PCT/US2023/083326 | J21: GURGAON | K21: 45831 | L21: 44921 | M21: 45839 | O21: 45839 | P21: Nikhil K R | Q21: M Vijaya Lakshmi | R21: RFE FILED
A22: 21 | B22: IP88072 | C22: 202541062777 | D22: HEXITRONICS AUTOMATION LLP | E22: PLEASE PROVIDE | F22: India | G22: HEXITRONICS AUTOMATION LLP | H22: METHOD AND SYSTEM FOR AUTO-CONFIGURABLE IOT DEVICES WITH DYNAMIC DASHBOARD GENERATION | I22: Provisional | J22: GURGAON | K22: 45825 | L22: 45839 | M22: 45839 | N22: 46784 | P22: Kshama Gaitonde | Q22: Mani V S | R22: PROVISIONAL FILED
A23: 22 | B23: IP88114 | C23: 202517062625 | D23: PEARCE IP | E23: 25900INP00 | F23: New Zealand | G23: WEIR SCIENCE LIMITED | H23: POLLEN-BASED COMPOSITIONS AND EXTRACTS FOR STIMULATING HYALURONIC ACID PRODUCTION PCT/NZ2023/050143 | J23: GURGAON | K23: 45826 | L23: 44897 | M23: 45839 | O23: 45839 | P23: Sachin Bindal | Q23: Chetna Veer | R23: RFE FILED
A24: 23 | B24: IP85280 | C24: 202511063083 | D24: The Director ICAR NIVEDI | E24: PLEASE PROVIDE | F24: India | G24: INDIAN COUNCIL OF AGRICULTURAL RESEARCH (ICAR) | H24: RECOMBINANT A27L PROTEIN, A KIT AND AN ASSAY FOR IDENTIFYING LUMPY SKIN DISEASE VIRUS (LSDV) | I24: Complete Filed | J24: BANGALORE | K24: 45687 | L24: 45840 | M24: 45840 | O24: 45917 | P24: Samriti Sanjgotra | Q24: Nitika Anand | R24: UNDER EXAMINATION
A25: 24 | B25: IP87102 | C25: 202541063209 | D25: ABB SWITZERLAND LTD. | E25: P241066IN01 | F25: Switzerland | G25: ABB SCHWEIZ AG | H25: METHOD AND APPARATUS FOR RECOMMENDING COLLABORATIVE LEARNING TECHNIQUE | I25: Complete Filed | J25: GURGAON | K25: 45771 | L25: 45840 | M25: 45840 | O25: 45840 | P25: Manju Thomas | Q25: Ravi Mishra | R25: RFE FILED
A26: 25 | B26: IP87822 | C26: 202517063207 | D26: Visa Inc. | E26: 6849IN02 | F26: United States Of America | G26: VISA INTERNATIONAL SERVICE ASSOCIATION | H26: SYSTEM AND METHOD FOR A NETWORK AUTHENTICATION WITH DEVICE LEVEL AUTHENTICATION CONTROLS PCT/US2023/083491 | J26: GURGAON | K26: 45812 | L26: 44908 | M26: 45840 | O26: 45840 | P26: Neilotpal Mukhopadhyay | Q26: Kamlesh Negi | R26: RFE FILED
A27: 26 | B27: IP87698 | C27: 202517063108 | D27: V.O. PATENTS & TRADEMARKS | E27: P133519IN00 | F27: Netherlands | G27: RIJKSUNIVERSITEIT GRONINGEN | H27: NANOBODY-FUNCTIONALIZED BIOLOGICAL NANOPORES AND MEANS AND METHODS RELATED THERETO PCT/NL2023/050633 | J27: GURGAON | K27: 45806 | L27: 44897 | M27: 45840 | O27: 45840 | P27: Samriti Sanjgotra | Q27: Nitika Anand | R27: RFE FILED
A28: 27 | B28: IP88305 | C28: 202547063115 | D28: QUALCOMM INCORPORATED | E28: 2301341IN | F28: United States Of America | G28: QUALCOMM INCORPORATED | H28: SIGNALING DESIGN FOR TD BEAM PREDICTION WITH FLEXIBLE MEASUREMENT AND PREDICTION CYCLES PCT/CN2023/076717 | J28: GURGAON | K28: 45834 | L28: 45840 | M28: 45840 | O28: 45840 | P28: Kshama Gaitonde | Q28: Mani V S | R28: RFE FILED
A29: 28 | B29: IP88309 | C29: 202547063268 | D29: QUALCOMM INCORPORATED | E29: 2301225IN | F29: United States Of America | G29: QUALCOMM INCORPORATED | H29: DELTA CONFIGURATION FOR LAYER 1/LAYER 2 TRIGGERED MOBILITY PCT/US2024/011979 | J29: GURGAON | K29: 45834 | L29: 44972 | M29: 45840 | O29: 45840 | P29: Kshama Gaitonde | Q29: Mani V S | R29: RFE FILED
A30: 29 | B30: IP88312 | C30: 202547063013 | D30: QUALCOMM INCORPORATED | E30: 2302648IN | F30: United States Of America | G30: QUALCOMM INCORPORATED | H30: MODEL SELECTION AND DELIVERY PCT/US2024/011694 | J30: GURGAON | K30: 45834 | L30: 44971 | M30: 45840 | O30: 45840 | P30: Harshitha R | Q30: Chaitra K G | R30: RFE FILED
A31: 30 | B31: IP88314 | C31: 202547063119 | D31: QUALCOMM INCORPORATED | E31: 2302794IN | F31: United States Of America | G31: QUALCOMM INCORPORATED | H31: RELAY ASSISTED FULL DUPLEX RELAY FROM NETWORK TO REMOTE UE IN SIDELINK MODE 1 PCT/US2024/016896 | J31: GURGAON | K31: 45834 | L31: 44985 | M31: 45840 | O31: 45840 | P31: Yeshwanth Thirunagari | Q31: Sarla Bhavani | R31: RFE FILED
A32: 31 | B32: IP88404 | C32: 202517063043 | D32: QUALCOMM INCORPORATED | E32: 2301194IN | F32: United States Of America | G32: QUALCOMM INCORPORATED | H32: ASYMMETRIC CONFIDENCE LEVEL FOR PREDICTIVE BEAM MANAGEMENT PCT/CN2023/076370 | J32: GURGAON | K32: 45839 | L32: 45840 | M32: 45840 | O32: 45840 | P32: Sanjit Kumar | Q32: Anand Yenurkar | R32: RFE FILED
A33: 32 | B33: IP87908 | C33: 202547063118 | D33: BOZICEVIC FIELD & FRANCIS LLP | E33: BERK-480IN | F33: United States Of America | G33: THE REGENTS OF THE UNIVERSITY OF CALIFORNIA | H33: INHIBITORY NUCLEIC ACIDS AND METHODS OF USE THEREOF PCT/US2023/082556 | J33: GURGAON | K33: 45814 | L33: 44902 | M33: 45840 | O33: 45840 | P33: Sneha Menon | Q33: Renuka R | R33: RFE FILED
A34: 33 | B34: IP88173 | C34: 202517063014 | D34: YOU ME PATENT & LAW FIRM | E34: OPP20244104IN | F34: Korea | G34: LG ENERGY SOLUTION, LTD. | H34: ENERGY STORAGE SYSTEM, AND PROTECTION DEVICE AND PROTECTION METHOD THEREOF PCT/KR2024/011757 | J34: GURGAON | K34: 45827 | L34: 45252 | M34: 45840 | O34: 45840 | P34: Vivek Atwal | Q34: Umesh Sharma | R34: RFE FILED
A35: 34 | B35: IP87646 | C35: 202517063099 | D35: SELIGSOHN GABRIELI BENSHAFRUT & CO. | E35: SOL-P-80950WOIN | F35: Israel | G35: SOLUTUM TECHNOLOGIES LTD | H35: BIODEGRADABLE AND BARRIER PVOH-BASED MATERIALS AND PRODUCTS MADE THEREFROM PCT/IL2023/051310 | J35: GURGAON | K35: 45803 | L35: 44922 | M35: 45840 | O35: 45840 | P35: Yameeni Sarothia | Q35: Arub Mistree | R35: RFE FILED
A36: 35 | B36: IP87971 | C36: 202517063177 | D36: CISCO TECHNOLOGY, INC. | E36: C/P/1034640/IN/PCT/1 | F36: United States Of America | G36: CISCO TECHNOLOGY, INC. | H36: SOFTWARE-DEFINED DEVICE TRACKING IN NETWORK FABRICS PCT/US2023/082841 | J36: GURGAON | K36: 45819 | L36: 44902 | M36: 45840 | O36: 45840 | P36: Hrudya Ravula | Q36: Prema Latha | R36: RFE FILED
A37: 36 | B37: IP88291 | C37: 202517063150 | D37: DONALDSON COMPANY INC | E37: 00011014-IN01 | F37: United States Of America | G37: DONALDSON COMPANY INC | H37: FILTER ELEMENTS, RELATED FILTER ASSEMBLY AND FILTER PACKAGE PCT/US2024/015821 | J37: GURGAON | K37: 45833 | L37: 44971 | M37: 45840 | O37: 45840 | P37: Himanshu Singh | Q37: Komal | R37: RFE FILED
A38: 37 | B38: IP86453 | C38: 202541063217 | D38: TITAN COMPANY LIMITED | E38: PLEASE PROVIDE | F38: India | G38: TITAN COMPANY LIMITED | H38: A TIMEPIECE | I38: Complete Filed | J38: GURGAON | K38: 45736 | L38: 45840 | M38: 45840 | O38: 45840 | P38: Alok Hegde | Q38: Navya N | R38: RFE FILED
A39: 38 | B39: IP87164 | C39: 202511063152 | D39: ICAR-CENTRAL SHEEP & WOOL RESEARCH INSTITUTE | E39: PLEASE PROVIDE | F39: India | G39: INDIAN COUNCIL OF AGRICULTURAL RESEARCH | H39: A WOOL FIBRE BLEND, ARTICLES AND METHODS THEREOF | I39: Provisional | J39: GURGAON | K39: 45775 | L39: 45840 | M39: 45840 | N39: 46785 | P39: Niharika Singh | Q39: Vandana . | R39: PROVISIONAL FILED
A40: 39 | B40: IP86564 | C40: 202517063157 | D40: KIP PATENT LAW FIRM | E40: 24PCTIN985 | F40: Korea | G40: LG ENERGY SOLUTION, LTD. | H40: ANODE, ANODE DAM COATING COMPOSITION, AND LITHIUM SECONDARY BATTERY PCT/KR2024/014546 | J40: GURGAON | K40: 45741 | L40: 45195 | M40: 45840 | O40: 45841 | P40: Toral Chauhan | Q40: Renu Rani | R40: RFE FILED
A41: 40 | B41: IP86545 | C41: 202514063111 | D41: KORYO IP & LAW | E41: LO-332099-IN | F41: Korea | G41: SAMSUNG DISPLAY CO., LTD. | H41: DEPOSITION APPARATUS AND DEPOSITION METHOD USING THE SAME | J41: GURGAON | K41: 45741 | L41: 45477 | M41: 45840 | N41: 46422 | P41: Mohamed Ghouse | Q41: Ravi Prakashan PK | R41: APPLICATION FILED
A42: 41 | B42: IP88292 | C42: 202517063039 | D42: PHIL & ONZI | E42: OVP2425625IN | F42: Korea | G42: LG ENERGY SOLUTION, LTD. | H42: ELECTRODE PRODUCTION DEVICE AND BATTERY CELL INCLUDING ELECTRODE PRODUCED USING SAME, AND BATTERY PACK AND VEHICLE INCLUDING BATTERY CELL PCT/KR2024/009693 | J42: GURGAON | K42: 45833 | L42: 45191 | M42: 45840 | O42: 45840 | P42: Piyush Joshi | Q42: Sanjana Jha | R42: RFE FILED
A43: 42 | B43: IP87823 | C43: 202547063190 | D43: FOX ROTHSCHILD LLP | E43: 104536.04242 | F43: United States Of America | G43: LIVEO RESEARCH AG | H43: PUSH THROUGH BLISTER PACKAGE WITH PLASTIC LIDDING PCT/IB2023/062214 | J43: GURGAON | K43: 45812 | L43: 44900 | M43: 45840 | O43: 45840 | P43: Nikhil K R | Q43: M Vijaya Lakshmi | R43: RFE FILED
A44: 43 | B44: IP88300 | C44: 202547063128 | D44: AVAMMUNE LIFESCIENCES PRIVATE LIMITED | E44: PLEASE PROVIDE | F44: India | G44: AVAMMUNE THERAPEUTICS INC. | H44: ADAR1 INHIBITORS AND METHODS OF USING THE SAME PCT/IN2023/051116 | J44: BANGALORE | K44: 45834 | L44: 44897 | M44: 45840 | O44: 45840 | P44: Yoganjaneyulu Kasetti | Q44: Gargi Bhattacharjee | R44: RFE FILED
A45: 44 | B45: IP86935 | C45: 202547063166 | D45: Focalworks Corporation | E45: RKT-70077IN | F45: Japan | G45: RAKUTEN MOBILE, INC. | H45: DESIGNATION OF ANALYSIS OBJECT IN ESTIMATING COMPETENT AREA OF EMERGENCY CALLS PCT/JP2023/013647 | J45: GURGAON | K45: 45763 | L45: 44932 | M45: 45840 | O45: 45840 | P45: Sunidhi A B | Q45: Esha Kapoor | R45: RFE FILED
A46: 45 | B46: IP88443 | C46: 202548063371 | D46: Y.P. LEE, MOCK & PARTNERS | E46: SH-58327-IND1-DMC | F46: Korea | G46: SAMSUNG ELECTRONICS CO. LTD. | H46: APPARATUSES FOR ENCODING AND DECODING IMAGE, AND METHODS FOR ENCODING AND DECODING IMAGE THEREBY | J46: GURGAON | K46: 45840 | L46: 45841 | M46: 45841 | O46: 45841 | P46: Neilotpal Mukhopadhyay | Q46: Kamlesh Negi | R46: RFE FILED
A47: 46 | B47: IP88444 | C47: 202548063417 | D47: Y.P. LEE, MOCK & PARTNERS | E47: SH-58327-IND2-DMC | F47: Korea | G47: SAMSUNG ELECTRONICS CO. LTD. | H47: APPARATUSES FOR ENCODING AND DECODING IMAGE, AND METHODS FOR ENCODING AND DECODING IMAGE THEREBY | J47: GURGAON | K47: 45840 | L47: 45841 | M47: 45841 | O47: 45842 | P47: Neilotpal Mukhopadhyay | Q47: Kamlesh Negi | R47: RFE FILED
A48: 47 | B48: IP88445 | C48: 202548063378 | D48: Y.P. LEE, MOCK & PARTNERS | E48: SH-58327-IND3-DMC | F48: Korea | G48: SAMSUNG ELECTRONICS CO. LTD. | H48: APPARATUSES FOR ENCODING AND DECODING IMAGE, AND METHODS FOR ENCODING AND DECODING IMAGE THEREBY | J48: GURGAON | K48: 45840 | L48: 45841 | M48: 45841 | O48: 45841 | P48: Neilotpal Mukhopadhyay | Q48: Kamlesh Negi | R48: RFE FILED
A49: 48 | B49: IP88446 | C49: 202548063382 | D49: Y.P. LEE, MOCK & PARTNERS | E49: SH-58327-IND4-DMC | F49: Korea | G49: SAMSUNG ELECTRONICS CO. LTD. | H49: APPARATUSES FOR ENCODING AND DECODING IMAGE, AND METHODS FOR ENCODING AND DECODING IMAGE THEREBY | J49: GURGAON | K49: 45840 | L49: 45841 | M49: 45841 | O49: 45841 | P49: Sunidhi A B | Q49: Esha Kapoor | R49: RFE FILED
A50: 49 | B50: IP88417 | C50: 202517063331 | D50: QUALCOMM INCORPORATED | E50: 2300512IN | F50: United States Of America | G50: QUALCOMM INCORPORATED | H50: A FRAMES PER SECOND (FPS) CONTROL SCHEME PCT/CN2023/075371 | J50: GURGAON | K50: 45839 | L50: 45841 | M50: 45841 | O50: 45841 | P50: Sonali Mewar | Q50: Arun Kumar | R50: RFE FILED
A51: 50 | B51: IP88313 | C51: 202547063341 | D51: QUALCOMM INCORPORATED | E51: 2302656IN | F51: United States Of America | G51: QUALCOMM INCORPORATED | H51: EVENT-BASED LAYER 1 MEASUREMENT REPORTING PCT/US2024/012698 | J51: GURGAON | K51: 45834 | L51: 44981 | M51: 45841 | O51: 45841 | P51: Manish Sharma | Q51: Neha Kumari | R51: RFE FILED
A52: 51 | B52: IP87594 | C52: 202547063553 | D52: Kangxin Partners.P.C | E52: PN314931FPSW | F52: China | G52: SHENZHEN INCRECARE BIOTECH CO. LTD | H52: SAMPLE CONVEYING SYSTEM PCT/CN2023/128538 | J52: GURGAON | K52: 45799 | L52: 44924 | M52: 45841 | O52: 45841 | P52: Raghavendra Y | Q52: Rajni Rani | R52: RFE FILED
A53: 52 | B53: IP87596 | C53: 202547063385 | D53: Kangxin Partners.P.C | E53: PN314937FPSW | F53: China | G53: SHENZHEN INCRECARE BIOTECH CO. LTD | H53: AUTOMATIC SAMPLE ANALYSIS APPARATUS PCT/CN2023/134132 | J53: GURGAON | K53: 45799 | L53: 44924 | M53: 45841 | O53: 45841 | P53: Raghavendra Y | Q53: Rajni Rani | R53: RFE FILED
A54: 53 | B54: IP86392 | C54: 202514063311 | D54: KORYO IP & LAW | E54: LO-331474-IN | F54: Korea | G54: SAMSUNG DISPLAY CO., LTD. | H54: DISPLAY PANEL AND ELECTRONIC DEVICE | J54: GURGAON | K54: 45734 | L54: 45478 | M54: 45841 | N54: 46423 | P54: Siddhant Parvat | Q54: Sitarey . | R54: APPLICATION FILED
A55: 54 | B55: IP88347 | C55: 202517063537 | D55: IBM CORPORATION | E55: P202200269IN01 | F55: United States Of America | G55: INTERNATIONAL BUSINESS MACHINES CORPORATION | H55: FAST MAPPER RESTORE FOR FLUSH IN PROCESSOR PCT/CN2023/132295 | J55: GURGAON | K55: 45835 | L55: 44900 | M55: 45841 | O55: 45841 | P55: Aniket Nimbarte | Q55: Prajnya Poojari | R55: RFE FILED
A56: 55 | B56: IP88233 | C56: 202517063539 | D56: BAE, KIM & LEE IP GROUP | E56: 2023-OPLE-9066PC/IN/EKL | F56: Korea | G56: LG ENERGY SOLUTION, LTD. | H56: POSITIVE ELECTRODE SLURRY FOR LITHIUM SECONDARY BATTERY AND METHOD OF PREPARING POSITIVE ELECTRODE FOR LITHIUM SECONDARY BATTERY USING THE SAME PCT/KR2024/000426 | J56: GURGAON | K56: 45832 | L56: 44946 | M56: 45841 | O56: 45842 | P56: Isha Khanna | Q56: Sarabjeet Kaur | R56: RFE FILED
A57: 56 | B57: IP87388 | C57: 202517063901 | D57: KROHER STROBEL | E57: 13996 P 6575 IN -SM/YR | F57: Germany | G57: VVARDIS AG | H57: ORAL FILM WITH MULTIPLE REGIONS FOR THERAPY OF PERIODONTAL AND DENTAL DISEASES OR DISORDERS PCT/EP2023/085961 | J57: GURGAON | K57: 45785 | L57: 44909 | M57: 45842 | O57: 45842 | P57: Yameeni Sarothia | Q57: Arub Mistree | R57: RFE FILED
A58: 57 | B58: IP88240 | C58: 202517063842 | D58: Slingsby Partners LLP | E58: CMR01-133293IN | F58: United Kingdom | G58: CMR SURGICAL LIMITED | H58: CONTROL SYSTEM FOR A SURGICAL ROBOTIC SYSTEM PCT/GB2024/050429 | J58: GURGAON | K58: 45832 | L58: 44978 | M58: 45842 | O58: 45842 | P58: Shivakumar Angadi | Q58: Rajani Kumari | R58: RFE FILED
A59: 58 | B59: IP87582 | C59: 202547064163 | D59: Slingsby Partners LLP | E59: CMR01-132937IN | F59: United Kingdom | G59: CMR SURGICAL LIMITED | H59: CONTROL SYSTEM FOR A SURGICAL ROBOTIC SYSTEM PCT/GB2023/053152 | J59: BANGALORE | K59: 45799 | L59: 44901 | M59: 45842 | O59: 45842 | P59: Manju Thomas | Q59: Ravi Mishra | R59: RFE FILED
A60: 59 | B60: IP87464 | C60: 202517063792 | D60: SAINT GOBAIN ADFORS | E60: 2022401-IN-PCT | F60: France | G60: SAINT-GOBAIN ADFORS | H60: TEXTILE BONDED BY A BINDER BASED ON POLYELECTROLYTES HAVING OPPOSITE CHARGE POLARITIES PCT/EP2023/085857 | J60: GURGAON | K60: 45791 | L60: 44911 | M60: 45842 | O60: 45842 | P60: Naresh Kumar Jonnnalagadda | Q60: Kundan Sah | R60: RFE FILED
A61: 60 | B61: IP88426 | C61: 202541064030 | D61: Samsung R&D Institute India-Bangalore Pvt. Ltd. | E61: SRIB-20250225-002 | F61: India | G61: SAMSUNG ELECTRONICS CO., LTD. | H61: METHOD AND SYSTEM FOR PROVIDING A PERSONALIZED GAZE PREDICTION IN AR GLASSES WITHOUT EYE TRACKING | I61: Complete Filed | J61: GURGAON | K61: 45839 | L61: 45842 | M61: 45842 | O61: 46079 | P61: Pragya Deshbhratar | Q61: Revikumar Nair | R61: RFE FILED
A62: 61 | B62: IP88480 | C62: 202511064179 | D62: Samsung R&D Institute India-Bangalore Pvt. Ltd. | E62: SRIB-20250703-002 | F62: India | G62: SAMSUNG ELECTRONICS CO., LTD. | H62: METHOD AND SYSTEM FOR MANAGING MOBILE WIRELESS ACCESS BACKHAUL | I62: Complete Filed | J62: GURGAON | K62: 45841 | L62: 45842 | M62: 45842 | O62: 46183 | P62: Rupali Nagpure | Q62: Kamlesh Negi | R62: RFE FILED
A63: 62 | B63: IP88170 | C63: 202544064127 | D63: ABB SWITZERLAND LTD. | E63: P240495IN01 | F63: Switzerland | G63: ABB SCHWEIZ AG | H63: ELECTRIC FIELD CONTROLLER FOR VACUUM INTERRUPTER, AND VACUUM SWITCH | J63: GURGAON | K63: 45827 | L63: 45512 | M63: 45842 | O63: 45842 | P63: Raghavendra Y | Q63: Rajni Rani | R63: RFE FILED
A64: 63 | B64: IP86963 | C64: 202541064215 | D64: MERCEDES-BENZ INTELLECTUAL PROPERTY GMBH & CO KG | E64: 2025P00793 IN | F64: Germany | G64: MERCEDES-BENZ GROUP AG | H64: AN ONBOARD CHARGER (OBC) FOR CONTROLLING CHARGING OF DIRECT CURRENT (DC)-LINK CAPACITOR AND METHOD THEREOF | I64: Complete Filed | J64: GURGAON | K64: 45764 | L64: 45842 | M64: 45842 | N64: 46787 | P64: Riti Sethi | Q64: Manas Maity | R64: COMPLETE FILED
A65: 64 | B65: IP85648 | C65: 202541063903 | D65: AMRITA CENTRE FOR NANOSCIENCES & | E65: ASP-001500INP | F65: India | G65: AMRITA SCHOOL OF PHARMACY, AMRITA VISHWA VIDYAPEETHAM | H65: STEATOGENIC DIET COMPOSITION FOR RODENTS AND METHOD THEREOF | I65: Provisional | J65: CHENNAI | K65: 45707 | L65: 45842 | M65: 45842 | N65: 46787 | P65: Vidyasaral Murugan | Q65: R Praveen | R65: PROVISIONAL FILED
A66: 65 | B66: IP87480 | C66: 202517063906 | D66: KWANG AND JANG INTELLECTUAL PROPERTY LAW FIRM | E66: SE-022-12-031-WO0IN0 | F66: Korea | G66: SAMSUNG ELECTRONICS CO., LTD. | H66: DISPLAY MODULE INCLUDING STRUCTURE FOR REDUCING DAMAGE AND ELECTRONIC DEVICE COMPRISING SAME PCT/KR2023/017881 | J66: GURGAON | K66: 45792 | L66: 44937 | M66: 45842 | O66: 45842 | P66: Siddhant Parvat | Q66: Sitarey . | R66: RFE FILED
A67: 66 | B67: IP87351 | C67: 202547064121 | D67: VUEREAL INC | E67: 612-000077IN5PT | F67: Canada | G67: VUEREAL INC. | H67: OPTOELECTRONIC MICRODEVICE PCT/CA2023/051641 | J67: GURGAON | K67: 45784 | L67: 44907 | M67: 45842 | O67: 45842 | P67: Hrudya Ravula | Q67: Prema Latha | R67: RFE FILED
A68: 67 | B68: IP88439 | C68: 202541063856 | D68: RAKUTEN MOBILE INC | E68: PI25-00358IN01 | F68: Japan | G68: RAKUTEN MOBILE, INC. | H68: SMO-ORCHESTRATED HIERARCHICAL O-RU MANAGEMENT SCENARIOS | I68: Provisional | J68: GURGAON | K68: 45840 | L68: 45842 | M68: 45842 | N68: 46787 | P68: Abhimanyu Singh | Q68: Anand Yenurkar | R68: PROVISIONAL FILED
A69: 68 | B69: IP88366 | C69: 202547063795 | D69: QUALCOMM INCORPORATED | E69: 2302409IN | F69: United States Of America | G69: QUALCOMM INCORPORATED | H69: PROTOCOL-DATA-UNIT-SET-BASED DISCARDING OR PROCESSING PCT/US2024/010675 | J69: GURGAON | K69: 45838 | L69: 44971 | M69: 45842 | O69: 45842 | P69: Yeshwanth Thirunagari | Q69: Sarla Bhavani | R69: RFE FILED
A70: 69 | B70: IP88367 | C70: 202547064240 | D70: QUALCOMM INCORPORATED | E70: 2303169IN | F70: United States Of America | G70: QUALCOMM INCORPORATED | H70: FUNCTIONALITY BASED IMPLICIT ML INFERENCE PARAMETER-GROUP SWITCH FOR BEAM PREDICTION PCT/CN2023/121601 | J70: GURGAON | K70: 45838 | L70: 44981 | M70: 45842 | O70: 45842 | P70: Sreeya Reddy Arrapu | Q70: Prema Latha | R70: RFE FILED
A71: 70 | B71: IP88369 | C71: 202517063868 | D71: QUALCOMM INCORPORATED | E71: 2303334IN | F71: United States Of America | G71: QUALCOMM INCORPORATED | H71: TECHNIQUES FOR PERFORMING CELL RESELECTION PROCEDURES USING A LOW-POWER WAKE-UP RECEIVER PCT/CN2023/078586 | J71: GURGAON | K71: 45838 | L71: 45842 | M71: 45842 | O71: 45842 | P71: Sonali Mewar | Q71: Arun Kumar | R71: RFE FILED
A72: 71 | B72: IP88370 | C72: 202517064285 | D72: QUALCOMM INCORPORATED | E72: 2302962IN | F72: United States Of America | G72: QUALCOMM INCORPORATED | H72: SELECTION AND RESELECTION OF RESOURCES FOR TRANSMISSION PCT/US2023/081593 | J72: GURGAON | K72: 45838 | L72: 44974 | M72: 45842 | O72: 45842 | P72: Puja Raghav | Q72: Mohammad Sheikh | R72: RFE FILED
A73: 72 | B73: IP88371 | C73: 202517064292 | D73: QUALCOMM INCORPORATED | E73: 2207594IN | F73: United States Of America | G73: QUALCOMM INCORPORATED | H73: PERIODIC ADVERTISEMENT SUBFRAME ALLOCATION BASED ON TRANSMIT POWER PCT/US2023/082163 | J73: GURGAON | K73: 45838 | L73: 44963 | M73: 45842 | O73: 45842 | P73: Ankit Rawat | Q73: Esha Kapoor | R73: RFE FILED
A74: 73 | B74: IP88405 | C74: 202547064157 | D74: QUALCOMM INCORPORATED | E74: 2301195IN | F74: United States Of America | G74: QUALCOMM INCORPORATED | H74: OVERHEAD REDUCTION FOR COMPLEMENTARY CONFIDENCE LEVEL REPORTING IN BEAM PREDICTIONS PCT/CN2023/076425 | J74: GURGAON | K74: 45839 | L74: 45842 | M74: 45842 | O74: 45842 | P74: Abhimanyu Singh | Q74: Anand Yenurkar | R74: RFE FILED
A75: 74 | B75: IP88461 | C75: 202517063924 | D75: QUALCOMM INCORPORATED | E75: 2206712IN | F75: United States Of America | G75: QUALCOMM INCORPORATED | H75: PERIPHERAL DEVICES FOR REAL-TIME REQUESTS PCT/CN2023/077771 | J75: GURGAON | K75: 45841 | L75: 45842 | M75: 45842 | O75: 45842 | P75: Sanjit Kumar | Q75: Anand Yenurkar | R75: RFE FILED
A76: 75 | B76: IP86490 | C76: 202547064033 | D76: SUGHRUE MION PLLC | E76: F307339 | F76: United States Of America | G76: RAKUTEN MOBILE, INC. | H76: TARGET CELL PRIORITIZATION FOR LAYER 1/LAYER 2 TRIGGERED MOBILITY PCT/US2023/061177 | J76: GURGAON | K76: 45737 | L76: 45842 | M76: 45842 | O76: 45842 | P76: Kshama Gaitonde | Q76: Mani V S | R76: RFE FILED
A77: 76 | B77: IP87013 | C77: 202517063840 | D77: PLASSERAUD IP | E77: B2202372WOIN | F77: France | G77: ORGANIK KIMYA SANAYI VE TIC. A.S. | H77: WATERBORNE POLYMER COMPOSITION AND PREPARATION METHOD THEREOF PCT/EP2022/086314 | J77: GURGAON | K77: 45768 | L77: 45842 | M77: 45842 | O77: 45842 | P77: Yameeni Sarothia | Q77: Arub Mistree | R77: RFE FILED
A78: 77 | B78: IP87731 | C78: 202547064003 | D78: MARKS & CLERK LLP | E78: PC932435IN | F78: United Kingdom | G78: RESURRECT BIO LTD | H78: METHODS OF MODULATING IMMUNE FUNCTION IN PLANTS PCT/EP2023/084349 | J78: GURGAON | K78: 45807 | L78: 44900 | M78: 45842 | O78: 45842 | P78: Sneha Menon | Q78: Renuka R | R78: RFE FILED
A79: 78 | B79: IP88375 | C79: 202541064056 | D79: HAYNES AND BOONE LLP | E79: 59103.145PV01 | F79: United States Of America | G79: BLACKROCK FINANCE INC. | H79: SYSTEMS AND METHODS FOR ORCHESTRATING AUTOMATED END-TO-END DATA FLOWS | I79: Provisional | J79: GURGAON | K79: 45838 | L79: 45842 | M79: 45842 | N79: 46787 | P79: Manju Thomas | Q79: Ravi Mishra | R79: ABANDONED
A80: 79 | B80: IP87890 | C80: 202547064145 | D80: FOLEY & LARDNER LLP | E80: 106556-0215 | F80: United States Of America | G80: FUJIFILM Biosciences Inc. | H80: SYSTEM AND METHOD FOR LIFTING AND ORIENTING A CHAMBER PCT/US2023/082584 | J80: GURGAON | K80: 45814 | L80: 44901 | M80: 45842 | O80: 45842 | P80: Bharath S | Q80: Suyoga SNK | R80: RFE FILED
A81: 80 | B81: IP88316 | C81: 202517063869 | D81: CN-KNOWHOW INTELLECTUAL PROPERTY AGENT LIMITED | E81: KHP2531110138.5INP | F81: China | G81: DATANG MOBILE COMMUNICATIONS EQUIPMENT CO., LTD. | H81: BEAM INDICATION METHOD, APPARATUS, AND DEVICE PCT/CN2023/113795 | J81: GURGAON | K81: 45834 | L81: 44925 | M81: 45842 | O81: 45842 | P81: Riti Sethi | Q81: Manas Maity | R81: RFE FILED
A82: 81 | B82: IP88043 | C82: 202514063967 | D82: GALBAIAN INTELLECTUAL PROPERTY | E82: ULM067 IN | F82: Spain | G82: ULMA Packaging, S.Coop | H82: PACKAGING MACHINE | J82: GURGAON | K82: 45821 | L82: 45512 | M82: 45842 | N82: 46454 | P82: Amit . | Q82: Nitesh Bishwakarma | R82: APPLICATION FILED
A83: 82 | B83: IP86058 | C83: 202547064220 | D83: Visa Inc. | E83: 6211IN01 | F83: United States Of America | G83: VISA INTERNATIONAL SERVICE ASSOCIATION | H83: METHOD AND SYSTEM FOR AUTOMATIC PAYMENT METHOD TRANSMISSION TO MERCHANTS PCT/IB2022/061765 | J83: GURGAON | K83: 45727 | L83: 45842 | M83: 45842 | O83: 45842 | P83: Mohamed Ghouse | Q83: Ravi Prakashan PK | R83: RFE FILED
A84: 83 | B84: IP87053 | C84: 202541064082 | D84: STRING BIO PRIVATE LIMITED | E84: PLEASE PROVIDE | F84: India | G84: STRING Bio Private Limited | H84: SYSTEM FOR PRODUCING VALUE ADDED PRODUCTS FROM METHANE (CH4) AND CARBON DIOXIDE (CO2) | I84: Provisional | J84: BANGALORE | K84: 45770 | L84: 45842 | M84: 45842 | N84: 46787 | P84: Revanth K | Q84: Preeti Shivaji Shindhe | R84: PROVISIONAL FILED
A85: 84 | B85: IP87086 | C85: 202541063876 | D85: Centre for Industrial Consultancy | E85: SR NO.: S 2025-26/2219 & THE IDF NO. 3263 | F85: India | G85: INDIAN INSTITUTE OF TECHNOLOGY MADRAS (IIT Madras) | H85: A SYSTEM FOR SUPPLYING FEED TO A POWER GENERATION UNIT OF A POWER PLANT | I85: Complete Filed | J85: CHENNAI | K85: 45771 | L85: 45842 | M85: 45842 | O85: 45842 | P85: Sesha Sai Charan Tej Karasu | Q85: M Vijaya Lakshmi | R85: UNDER EXAMINATION
A86: 85 | B86: IP87087 | C86: 202541063893 | D86: Centre for Industrial Consultancy | E86: SR NO.: S 2025-26/2222 & THE IDF NO. 3360 | F86: India | G86: INDIAN INSTITUTE OF TECHNOLOGY MADRAS (IIT Madras) | H86: A POWER GENERATION UNIT AND A SYSTEM THEREOF | I86: Complete Filed | J86: CHENNAI | K86: 45771 | L86: 45842 | M86: 45842 | O86: 45845 | P86: Suraj Sadulnagar | Q86: Sahiti Devaki | R86: HEARING
A87: 86 | B87: IP87088 | C87: 202541063851 | D87: Centre for Industrial Consultancy | E87: SR NO.: S 2025-26/2221 & THE IDF NO. 3359 | F87: India | G87: INDIAN INSTITUTE OF TECHNOLOGY MADRAS (IIT Madras) | H87: A POWER GENERATION SYSTEM | I87: Complete Filed | J87: CHENNAI | K87: 45771 | L87: 45842 | M87: 45842 | O87: 45842 | P87: Alok Hegde | Q87: Navya N | R87: UNDER EXAMINATION
A88: 87 | B88: IP87089 | C88: 202541063979 | D88: Centre for Industrial Consultancy | E88: SR NO.: S 2025-26/2220 & THE IDF NO. 3358 | F88: India | G88: INDIAN INSTITUTE OF TECHNOLOGY MADRAS (IIT Madras) | H88: AN EXCAVATOR BUCKET FOR A BUCKET WHEEL EXCAVATOR OF A STACKER RECLAIMER UNIT | I88: Complete Filed | J88: CHENNAI | K88: 45771 | L88: 45842 | M88: 45842 | O88: 45842 | P88: Prashant Shrihari Auti | Q88: Varshini Gundu | R88: RE-FILED
A89: 88 | B89: IP87943 | C89: 202541064202 | D89: Centre for Industrial Consultancy | E89: SR NO.: S 2025-26/2291 & THE IDF NO. 3425 | F89: India | G89: INDIAN INSTITUTE OF TECHNOLOGY MADRAS (IIT Madras) | H89: A CONTAINER FOR ACCOMMODATING GRANULAR MATERIAL | I89: Complete Filed | J89: CHENNAI | K89: 45818 | L89: 45842 | M89: 45842 | O89: 45845 | P89: Prashant Shrihari Auti | Q89: Varshini Gundu | R89: RE-FILED
A90: 89 | B90: IP87154 | C90: 202531063908 | D90: TATA STEEL LIMITED | E90: 81087254 | F90: India | G90: TATA STEEL LIMITED | H90: METHOD AND SYSTEM FOR MANAGING POWER DISTRIBUTION | I90: Complete Filed | J90: GURGAON | K90: 45775 | L90: 45842 | M90: 45842 | O90: 45856 | P90: Kshama Gaitonde | Q90: Mani V S | R90: RFE FILED
A91: 90 | B91: IP88246 | C91: 202517064058 | D91: NOTARBARTOLO & GERVASI S.P.A. | E91: P023052IN-01 | F91: Italy | G91: GIULIANI S.P.A. | H91: COMPOSITION FOR THE MODIFIED RELEASE OF BIOLOGICAL POLYAMINES, IN PARTICULAR SPERMIDINE PCT/IB2023/062221 | J91: GURGAON | K91: 45832 | L91: 44901 | M91: 45842 | O91: 45842 | P91: Anjali Singh | Q91: Chetna Veer | R91: RFE FILED
A92: 91 | B92: IP88352 | C92: 202517063899 | D92: IBM CORPORATION | E92: P202201236IN01 | F92: United States Of America | G92: INTERNATIONAL BUSINESS MACHINES CORPORATION | H92: VOLTAGE DROOP AND OVERSHOOT MANAGEMENT USING NON-LINEAR SLOPE DETECTION PCT/EP2023/084108 | J92: GURGAON | K92: 45835 | L92: 44910 | M92: 45842 | O92: 45842 | P92: Hrudya Ravula | Q92: Prema Latha | R92: RFE FILED
A93: 92 | B93: IP87532 | C93: 202547064018 | D93: BARDEHLE PAGENBERG (S) | E93: P4974IN00 | F93: Spain | G93: AUTOTECH ENGINEERING, S.L. | H93: A UNITARY ROOF RING OF A VEHICLE FRAMEWORK PCT/EP2023/084348 | J93: GURGAON | K93: 45797 | L93: 44902 | M93: 45842 | O93: 45842 | P93: Sesha Sai Charan Tej Karasu | Q93: M Vijaya Lakshmi | R93: RFE FILED
A94: 93 | B94: IP87921 | C94: 202547064005 | D94: DEHNS | E94: 69.207.128004/06 | F94: United Kingdom | G94: NEXTERA AS | H94: MODIFIED PIX VECTOR CONSTRUCT PCT/EP2023/087102 | J94: GURGAON | K94: 45817 | L94: 44915 | M94: 45842 | O94: 45842 | P94: Niharika Singh | Q94: Vandana . | R94: RFE FILED
A95: 94 | B95: IP86303 | C95: 202517064146 | D95: VOSSIUS & PARTNER | E95: AF3796 IN | F95: Germany | G95: TECHNISCHE UNIVERSITÄT MÜNCHEN | H95: RADIOLABELED PSMA LIGAND COMPOUNDS AND PRECURSORS THEREOF PCT/EP2023/086504 | J95: GURGAON | K95: 45729 | L95: 44916 | M95: 45842 | O95: 45842 | P95: Indrani Adhikari | Q95: Sunil Gaur | R95: RFE FILED
A96: 95 | B96: IP88460 | C96: 202541064158 | D96: HAMILTON BROOK SMITH REYNOLDS | E96: 4316.1031-001 IN | F96: United States Of America | G96: DASSAULT SYSTEMES AMERICAS CORP | H96: GENERATIVE MULTI-DIMENSIONAL FINITE ELEMENT MODELING FROM LAYERED MATERIAL DESIGN | I96: Provisional | J96: GURGAON | K96: 45841 | L96: 45842 | M96: 45842 | N96: 46787 | P96: Manju Thomas | Q96: Ravi Mishra | R96: ABANDONED
A97: 96 | B97: IP87707 | C97: 202544064002 | D97: SCHAEFFLER TECHNOLOGIES AG & CO KG | E97: 2024P00499 IN (VTFR) / / PAW | F97: Germany | G97: SCHAEFFLER TECHNOLOGIES AG & CO. KG | H97: METHOD FOR MANAGING A GEAR SHIFT IN A GEARBOX | J97: GURGAON | K97: 45806 | L97: 45496 | M97: 45842 | O97: 45842 | P97: Bharath S | Q97: Suyoga SNK | R97: RFE FILED
A98: 97 | B98: IP88069 | C98: 202517063965 | D98: BAE, KIM & LEE IP GROUP | E98: 2023-OPLE-8420PC/IN/EKL/JWJ | F98: Korea | G98: LG ENERGY SOLUTION, LTD. | H98: BATTERY LIFE INFORMATION PROVIDING APPARATUS AND OPERATING METHOD THEREOF PCT/KR2023/019905 | J98: GURGAON | K98: 45824 | L98: 44916 | M98: 45842 | O98: 45842 | P98: Neilotpal Mukhopadhyay | Q98: Kamlesh Negi | R98: RFE FILED
A99: 98 | B99: IP88334 | C99: 202541064356 | D99: ABB SWITZERLAND LTD. | E99: P250515IN01 | F99: Switzerland | G99: ABB SCHWEIZ AG | H99: METHOD AND APPARATUS FOR RECOMMENDING OPERATIONAL TAGS FOR AN ASSET | I99: Complete Filed | J99: GURGAON | K99: 45835 | L99: 45843 | M99: 45843 | O99: 45895 | P99: Manju Thomas | Q99: Ravi Mishra | R99: RFE FILED
A100: 99 | B100: IP86997 | C100: 202517064352 | D100: SAKAI INTERNATIONAL PATENT OFFICE | E100: PMAA-242479-IN | F100: Japan | G100: MITSUBISHI ELECTRIC CORPORATION | H100: MOTOR CONTROLLER AND RAILROAD VEHICLE DRIVING SYSTEM PCT/JP2023/000090 | J100: GURGAON | K100: 45768 | L100: 45843 | M100: 45843 | O100: 45843 | P100: Ankur Saxena | Q100: Shalu Saxena | R100: RFE FILED
...
